[
  {
    "id": "rus_c1_101",
    "language_code": "ru",
    "level_tag": "C1_Vocabulary",
    "original_script": "Аргументация",
    "romanized_script": "Argumentatsiya",
    "meaning": "Gerekçelendirme / Kanıtlama süreci",
    "is_latin": false,
    "metadata": {
      "script_direction": "ltr"
    },
    "audioUrl": "/data/data/Russian/Audio/rus_c1_101_argumentatsiya.mp3"
  },
  {
    "id": "rus_c1_102",
    "language_code": "ru",
    "level_tag": "C1_Vocabulary",
    "original_script": "Заблуждение",
    "romanized_script": "Zablujdeniye",
    "meaning": "Yanılgı / Doğru sanılan yanlış",
    "is_latin": false,
    "metadata": {
      "script_direction": "ltr"
    },
    "audioUrl": "/data/data/Russian/Audio/rus_c1_102_zablujdeniye.mp3"
  },
  {
    "id": "rus_c1_103",
    "language_code": "ru",
    "level_tag": "C1_Vocabulary",
    "original_script": "Опровержение",
    "romanized_script": "Oproverjeniye",
    "meaning": "Çürütme / Aksini kanıtlama",
    "is_latin": false,
    "metadata": {
      "script_direction": "ltr"
    },
    "audioUrl": "/data/data/Russian/Audio/rus_c1_103_oproverjeniye.mp3"
  },
  {
    "id": "rus_c1_104",
    "language_code": "ru",
    "level_tag": "C1_Vocabulary",
    "original_script": "Противоречие",
    "romanized_script": "Protivoreçiye",
    "meaning": "Tezat / Çelişki",
    "is_latin": false,
    "metadata": {
      "script_direction": "ltr"
    },
    "audioUrl": "/data/data/Russian/Audio/rus_c1_104_protivore_iye.mp3"
  },
  {
    "id": "rus_c1_105",
    "language_code": "ru",
    "level_tag": "C1_Vocabulary",
    "original_script": "Закономерность",
    "romanized_script": "Zakonomernost",
    "meaning": "Doğal düzen / Nedensellik bağı",
    "is_latin": false,
    "metadata": {
      "script_direction": "ltr"
    },
    "audioUrl": "/data/data/Russian/Audio/rus_c1_105_zakonomernost.mp3"
  },
  {
    "id": "rus_c1_106",
    "language_code": "ru",
    "level_tag": "C1_Vocabulary",
    "original_script": "Взаимопонимание",
    "romanized_script": "Vzaimoponimaniye",
    "meaning": "Karşılıklı anlayış",
    "is_latin": false,
    "metadata": {
      "script_direction": "ltr"
    },
    "audioUrl": "/data/data/Russian/Audio/rus_c1_106_vzaimoponimaniye.mp3"
  },
  {
    "id": "rus_c1_107",
    "language_code": "ru",
    "level_tag": "C1_Vocabulary",
    "original_script": "Обязательство",
    "romanized_script": "Obyazatelstvo",
    "meaning": "Taahhüt / Yükümlülük",
    "is_latin": false,
    "metadata": {
      "script_direction": "ltr"
    },
    "audioUrl": "/data/data/Russian/Audio/rus_c1_107_obyazatelstvo.mp3"
  },
  {
    "id": "rus_c1_108",
    "language_code": "ru",
    "level_tag": "C1_Vocabulary",
    "original_script": "Полномочие",
    "romanized_script": "Polnomoçiye",
    "meaning": "Yetki / Selahiyet",
    "is_latin": false,
    "metadata": {
      "script_direction": "ltr"
    },
    "audioUrl": "/data/data/Russian/Audio/rus_c1_108_polnomo_iye.mp3"
  },
  {
    "id": "rus_c1_109",
    "language_code": "ru",
    "level_tag": "C1_Vocabulary",
    "original_script": "Учреждение",
    "romanized_script": "Uçrejdeniye",
    "meaning": "Kurum / Kuruluş / Müessese",
    "is_latin": false,
    "metadata": {
      "script_direction": "ltr"
    },
    "audioUrl": "/data/data/Russian/Audio/rus_c1_109_u_rejdeniye.mp3"
  },
  {
    "id": "rus_c1_110",
    "language_code": "ru",
    "level_tag": "C1_Vocabulary",
    "original_script": "Имущество",
    "romanized_script": "Imuşçestvo",
    "meaning": "Mülk / Mal varlığı",
    "is_latin": false,
    "metadata": {
      "script_direction": "ltr"
    },
    "audioUrl": "/data/data/Russian/Audio/rus_c1_110_imu_estvo.mp3"
  },
  {
    "id": "rus_c1_111",
    "language_code": "ru",
    "level_tag": "C1_Vocabulary",
    "original_script": "Благосостояние",
    "romanized_script": "Blagosostoyaniye",
    "meaning": "Refah / Gönenç",
    "is_latin": false,
    "metadata": {
      "script_direction": "ltr"
    },
    "audioUrl": "/data/data/Russian/Audio/rus_c1_111_blagosostoyaniye.mp3"
  },
  {
    "id": "rus_c1_112",
    "language_code": "ru",
    "level_tag": "C1_Vocabulary",
    "original_script": "Эффективность",
    "romanized_script": "Effektivnost",
    "meaning": "Etkililik / Verimlilik",
    "is_latin": false,
    "metadata": {
      "script_direction": "ltr"
    },
    "audioUrl": "/data/data/Russian/Audio/rus_c1_112_effektivnost.mp3"
  },
  {
    "id": "rus_c1_113",
    "language_code": "ru",
    "level_tag": "C1_Vocabulary",
    "original_script": "Интеграция",
    "romanized_script": "Integratsiya",
    "meaning": "Entegrasyon / Uyumlaşma",
    "is_latin": false,
    "metadata": {
      "script_direction": "ltr"
    },
    "audioUrl": "/data/data/Russian/Audio/rus_c1_113_integratsiya.mp3"
  },
  {
    "id": "rus_c1_114",
    "language_code": "ru",
    "level_tag": "C1_Vocabulary",
    "original_script": "Дифференциация",
    "romanized_script": "Differentsiatsiya",
    "meaning": "Farklılaşma / Ayrışma",
    "is_latin": false,
    "metadata": {
      "script_direction": "ltr"
    },
    "audioUrl": "/data/data/Russian/Audio/rus_c1_114_differentsiatsiya.mp3"
  },
  {
    "id": "rus_c1_115",
    "language_code": "ru",
    "level_tag": "C1_Vocabulary",
    "original_script": "Тенденция",
    "romanized_script": "Tendentsiya",
    "meaning": "Eğilim / Akım",
    "is_latin": false,
    "metadata": {
      "script_direction": "ltr"
    },
    "audioUrl": "/data/data/Russian/Audio/rus_c1_115_tendentsiya.mp3"
  },
  {
    "id": "rus_c1_116",
    "language_code": "ru",
    "level_tag": "C1_Vocabulary",
    "original_script": "Специфика",
    "romanized_script": "Spetsifika",
    "meaning": "Özgün nitelik / Kendine haslık",
    "is_latin": false,
    "metadata": {
      "script_direction": "ltr"
    },
    "audioUrl": "/data/data/Russian/Audio/rus_c1_116_spetsifika.mp3"
  },
  {
    "id": "rus_c1_117",
    "language_code": "ru",
    "level_tag": "C1_Vocabulary",
    "original_script": "Критерий",
    "romanized_script": "Kriteriy",
    "meaning": "Ölçüt / Kıstas",
    "is_latin": false,
    "metadata": {
      "script_direction": "ltr"
    },
    "audioUrl": "/data/data/Russian/Audio/rus_c1_117_kriteriy.mp3"
  },
  {
    "id": "rus_c1_118",
    "language_code": "ru",
    "level_tag": "C1_Vocabulary",
    "original_script": "Потенциал",
    "romanized_script": "Potentsial",
    "meaning": "Potansiyel / Gizil güç",
    "is_latin": false,
    "metadata": {
      "script_direction": "ltr"
    },
    "audioUrl": "/data/data/Russian/Audio/rus_c1_118_potentsial.mp3"
  },
  {
    "id": "rus_c1_119",
    "language_code": "ru",
    "level_tag": "C1_Vocabulary",
    "original_script": "Перспектива",
    "romanized_script": "Perspektiva",
    "meaning": "Gelecek görünümü / Ufuk",
    "is_latin": false,
    "metadata": {
      "script_direction": "ltr"
    },
    "audioUrl": "/data/data/Russian/Audio/rus_c1_119_perspektiva.mp3"
  },
  {
    "id": "rus_c1_120",
    "language_code": "ru",
    "level_tag": "C1_Vocabulary",
    "original_script": "Альтернатива",
    "romanized_script": "Alternativa",
    "meaning": "Alternatif / Diğer yol",
    "is_latin": false,
    "metadata": {
      "script_direction": "ltr"
    },
    "audioUrl": "/data/data/Russian/Audio/rus_c1_120_alternativa.mp3"
  },
  {
    "id": "rus_c1_121",
    "language_code": "ru",
    "level_tag": "C1_Vocabulary",
    "original_script": "Опровергать",
    "romanized_script": "Oprovergat",
    "meaning": "Aksini kanıtlamak / Tekzip etmek",
    "is_latin": false,
    "metadata": {
      "script_direction": "ltr"
    },
    "audioUrl": "/data/data/Russian/Audio/rus_c1_121_oprovergat.mp3"
  },
  {
    "id": "rus_c1_122",
    "language_code": "ru",
    "level_tag": "C1_Vocabulary",
    "original_script": "Обосновывать",
    "romanized_script": "Obosnovıvat",
    "meaning": "Gerekçelendirmek / Dayanak sunmak",
    "is_latin": false,
    "metadata": {
      "script_direction": "ltr"
    },
    "audioUrl": "/data/data/Russian/Audio/rus_c1_122_obosnov_vat.mp3"
  },
  {
    "id": "rus_c1_123",
    "language_code": "ru",
    "level_tag": "C1_Vocabulary",
    "original_script": "Препятствовать",
    "romanized_script": "Prepyatstvovat",
    "meaning": "Köstek olmak / Engellemek",
    "is_latin": false,
    "metadata": {
      "script_direction": "ltr"
    },
    "audioUrl": "/data/data/Russian/Audio/rus_c1_123_prepyatstvovat.mp3"
  },
  {
    "id": "rus_c1_124",
    "language_code": "ru",
    "level_tag": "C1_Vocabulary",
    "original_script": "Способствовать",
    "romanized_script": "Sposobstvovat",
    "meaning": "Ön ayak olmak / Katkı sağlamak",
    "is_latin": false,
    "metadata": {
      "script_direction": "ltr"
    },
    "audioUrl": "/data/data/Russian/Audio/rus_c1_124_sposobstvovat.mp3"
  },
  {
    "id": "rus_c1_125",
    "language_code": "ru",
    "level_tag": "C1_Vocabulary",
    "original_script": "Взаимодействовать",
    "romanized_script": "Vzaimodeystvovat",
    "meaning": "Etkileşime girmek / Ortak çalışmak",
    "is_latin": false,
    "metadata": {
      "script_direction": "ltr"
    },
    "audioUrl": "/data/data/Russian/Audio/rus_c1_125_vzaimodeystvovat.mp3"
  },
  {
    "id": "rus_c1_126",
    "language_code": "ru",
    "level_tag": "C1_Vocabulary",
    "original_script": "Функционировать",
    "romanized_script": "Funktsionirovat",
    "meaning": "İşlev göstermek / Çalışmak",
    "is_latin": false,
    "metadata": {
      "script_direction": "ltr"
    },
    "audioUrl": "/data/data/Russian/Audio/rus_c1_126_funktsionirovat.mp3"
  },
  {
    "id": "rus_c1_127",
    "language_code": "ru",
    "level_tag": "C1_Vocabulary",
    "original_script": "Трансформировать",
    "romanized_script": "Transformirovat",
    "meaning": "Yapısını değiştirmek / Dönüştürmek",
    "is_latin": false,
    "metadata": {
      "script_direction": "ltr"
    },
    "audioUrl": "/data/data/Russian/Audio/rus_c1_127_transformirovat.mp3"
  },
  {
    "id": "rus_c1_128",
    "language_code": "ru",
    "level_tag": "C1_Vocabulary",
    "original_script": "Анализировать",
    "romanized_script": "Analizirovat",
    "meaning": "Çözümlemek / Analiz etmek",
    "is_latin": false,
    "metadata": {
      "script_direction": "ltr"
    },
    "audioUrl": "/data/data/Russian/Audio/rus_c1_128_analizirovat.mp3"
  },
  {
    "id": "rus_c1_129",
    "language_code": "ru",
    "level_tag": "C1_Vocabulary",
    "original_script": "Формировать",
    "romanized_script": "Formirovat",
    "meaning": "Biçimlendirmek / Yapılandırmak",
    "is_latin": false,
    "metadata": {
      "script_direction": "ltr"
    },
    "audioUrl": "/data/data/Russian/Audio/rus_c1_129_formirovat.mp3"
  },
  {
    "id": "rus_c1_130",
    "language_code": "ru",
    "level_tag": "C1_Vocabulary",
    "original_script": "Реализовать",
    "romanized_script": "Realizovat",
    "meaning": "Hayata geçirmek / Gerçekleştirmek",
    "is_latin": false,
    "metadata": {
      "script_direction": "ltr"
    },
    "audioUrl": "/data/data/Russian/Audio/rus_c1_130_realizovat.mp3"
  },
  {
    "id": "rus_c1_131",
    "language_code": "ru",
    "level_tag": "C1_Vocabulary",
    "original_script": "Стимулировать",
    "romanized_script": "Stimulirovat",
    "meaning": "Teşvik etmek / Güdülemek",
    "is_latin": false,
    "metadata": {
      "script_direction": "ltr"
    },
    "audioUrl": "/data/data/Russian/Audio/rus_c1_131_stimulirovat.mp3"
  },
  {
    "id": "rus_c1_132",
    "language_code": "ru",
    "level_tag": "C1_Vocabulary",
    "original_script": "Координировать",
    "romanized_script": "Koordinirovat",
    "meaning": "Eş güdüm sağlamak / Koordine etmek",
    "is_latin": false,
    "metadata": {
      "script_direction": "ltr"
    },
    "audioUrl": "/data/data/Russian/Audio/rus_c1_132_koordinirovat.mp3"
  },
  {
    "id": "rus_c1_133",
    "language_code": "ru",
    "level_tag": "C1_Vocabulary",
    "original_script": "Регулировать",
    "romanized_script": "Regulirovat",
    "meaning": "Mevzuata uygun düzenlemek",
    "is_latin": false,
    "metadata": {
      "script_direction": "ltr"
    },
    "audioUrl": "/data/data/Russian/Audio/rus_c1_133_regulirovat.mp3"
  },
  {
    "id": "rus_c1_134",
    "language_code": "ru",
    "level_tag": "C1_Vocabulary",
    "original_script": "Констатировать",
    "romanized_script": "Konstatirovat",
    "meaning": "Durum tespiti yapmak / Saptamak",
    "is_latin": false,
    "metadata": {
      "script_direction": "ltr"
    },
    "audioUrl": "/data/data/Russian/Audio/rus_c1_134_konstatirovat.mp3"
  },
  {
    "id": "rus_c1_135",
    "language_code": "ru",
    "level_tag": "C1_Vocabulary",
    "original_script": "Доминировать",
    "romanized_script": "Dominirovat",
    "meaning": "Egemen olmak / Üstünlük kurmak",
    "is_latin": false,
    "metadata": {
      "script_direction": "ltr"
    },
    "audioUrl": "/data/data/Russian/Audio/rus_c1_135_dominirovat.mp3"
  },
  {
    "id": "rus_c1_136",
    "language_code": "ru",
    "level_tag": "C1_Vocabulary",
    "original_script": "Манипулировать",
    "romanized_script": "Manipulirovat",
    "meaning": "Hileyle yönlendirmek / Manipüle etmek",
    "is_latin": false,
    "metadata": {
      "script_direction": "ltr"
    },
    "audioUrl": "/data/data/Russian/Audio/rus_c1_136_manipulirovat.mp3"
  },
  {
    "id": "rus_c1_137",
    "language_code": "ru",
    "level_tag": "C1_Vocabulary",
    "original_script": "Игнорировать",
    "romanized_script": "Ignorirovat",
    "meaning": "Görmezden gelmek / Yok saymak",
    "is_latin": false,
    "metadata": {
      "script_direction": "ltr"
    },
    "audioUrl": "/data/data/Russian/Audio/rus_c1_137_ignorirovat.mp3"
  },
  {
    "id": "rus_c1_138",
    "language_code": "ru",
    "level_tag": "C1_Vocabulary",
    "original_script": "Прогнозировать",
    "romanized_script": "Prognozirovat",
    "meaning": "Öngörmek / Tahminde bulunmak",
    "is_latin": false,
    "metadata": {
      "script_direction": "ltr"
    },
    "audioUrl": "/data/data/Russian/Audio/rus_c1_138_prognozirovat.mp3"
  },
  {
    "id": "rus_c1_139",
    "language_code": "ru",
    "level_tag": "C1_Vocabulary",
    "original_script": "Аргументировать",
    "romanized_script": "Argumentirovat",
    "meaning": "Tez savunmak / Kanıt göstermek",
    "is_latin": false,
    "metadata": {
      "script_direction": "ltr"
    },
    "audioUrl": "/data/data/Russian/Audio/rus_c1_139_argumentirovat.mp3"
  },
  {
    "id": "rus_c1_140",
    "language_code": "ru",
    "level_tag": "C1_Vocabulary",
    "original_script": "Дискутировать",
    "romanized_script": "Diskutirovat",
    "meaning": "Akademik tartışma yürütmek",
    "is_latin": false,
    "metadata": {
      "script_direction": "ltr"
    },
    "audioUrl": "/data/data/Russian/Audio/rus_c1_140_diskutirovat.mp3"
  },
  {
    "id": "rus_c1_141",
    "language_code": "ru",
    "level_tag": "C1_Vocabulary",
    "original_script": "Актуальный",
    "romanized_script": "Aktualnıy",
    "meaning": "Gündemde olan / Geçerli",
    "is_latin": false,
    "metadata": {
      "script_direction": "ltr"
    },
    "audioUrl": "/data/data/Russian/Audio/rus_c1_141_aktualn_y.mp3"
  },
  {
    "id": "rus_c1_142",
    "language_code": "ru",
    "level_tag": "C1_Vocabulary",
    "original_script": "Существенный",
    "romanized_script": "Suşçestvennıy",
    "meaning": "Esaslı / Büyük ölçüde önemli",
    "is_latin": false,
    "metadata": {
      "script_direction": "ltr"
    },
    "audioUrl": "/data/data/Russian/Audio/rus_c1_142_su_estvenn_y.mp3"
  },
  {
    "id": "rus_c1_143",
    "language_code": "ru",
    "level_tag": "C1_Vocabulary",
    "original_script": "Специфический",
    "romanized_script": "Spetsifiçeskiy",
    "meaning": "Kendine özgü / Nevi şahsına münhasır",
    "is_latin": false,
    "metadata": {
      "script_direction": "ltr"
    },
    "audioUrl": "/data/data/Russian/Audio/rus_c1_143_spetsifi_eskiy.mp3"
  },
  {
    "id": "rus_c1_144",
    "language_code": "ru",
    "level_tag": "C1_Vocabulary",
    "original_script": "Объективный",
    "romanized_script": "Obaktivnıy",
    "meaning": "Tarafsız / Nesnel",
    "is_latin": false,
    "metadata": {
      "script_direction": "ltr"
    },
    "audioUrl": "/data/data/Russian/Audio/rus_c1_144_obaktivn_y.mp3"
  },
  {
    "id": "rus_c1_145",
    "language_code": "ru",
    "level_tag": "C1_Vocabulary",
    "original_script": "Субъективный",
    "romanized_script": "Subektivnıy",
    "meaning": "Kişisel kanıya dayalı / Öznel",
    "is_latin": false,
    "metadata": {
      "script_direction": "ltr"
    },
    "audioUrl": "/data/data/Russian/Audio/rus_c1_145_subektivn_y.mp3"
  },
  {
    "id": "rus_c1_146",
    "language_code": "ru",
    "level_tag": "C1_Vocabulary",
    "original_script": "Абстрактный",
    "romanized_script": "Abstraktnıy",
    "meaning": "Düşünsel / Soyut kavramsal",
    "is_latin": false,
    "metadata": {
      "script_direction": "ltr"
    },
    "audioUrl": "/data/data/Russian/Audio/rus_c1_146_abstraktn_y.mp3"
  },
  {
    "id": "rus_c1_147",
    "language_code": "ru",
    "level_tag": "C1_Vocabulary",
    "original_script": "Конкретный",
    "romanized_script": "Konkretnıy",
    "meaning": "Belirli / Somut / Net",
    "is_latin": false,
    "metadata": {
      "script_direction": "ltr"
    },
    "audioUrl": "/data/data/Russian/Audio/rus_c1_147_konkretn_y.mp3"
  },
  {
    "id": "rus_c1_148",
    "language_code": "ru",
    "level_tag": "C1_Vocabulary",
    "original_script": "Адекватный",
    "romanized_script": "Adekvatnıy",
    "meaning": "Duruma tam oturan / Uygun",
    "is_latin": false,
    "metadata": {
      "script_direction": "ltr"
    },
    "audioUrl": "/data/data/Russian/Audio/rus_c1_148_adekvatn_y.mp3"
  },
  {
    "id": "rus_c1_149",
    "language_code": "ru",
    "level_tag": "C1_Vocabulary",
    "original_script": "Универсальный",
    "romanized_script": "Universalnıy",
    "meaning": "Genelgeçer / Evrensel",
    "is_latin": false,
    "metadata": {
      "script_direction": "ltr"
    },
    "audioUrl": "/data/data/Russian/Audio/rus_c1_149_universaln_y.mp3"
  },
  {
    "id": "rus_c1_150",
    "language_code": "ru",
    "level_tag": "C1_Vocabulary",
    "original_script": "Уникальный",
    "romanized_script": "Unikalnıy",
    "meaning": "Nevii şahsına münhasır / Biricik",
    "is_latin": false,
    "metadata": {
      "script_direction": "ltr"
    },
    "audioUrl": "/data/data/Russian/Audio/rus_c1_150_unikaln_y.mp3"
  },
  {
    "id": "rus_c1_151",
    "language_code": "ru",
    "level_tag": "C1_Vocabulary",
    "original_script": "Кардинальный",
    "romanized_script": "Kardinalnıy",
    "meaning": "Kökten / Çok büyük ve köklü",
    "is_latin": false,
    "metadata": {
      "script_direction": "ltr"
    },
    "audioUrl": "/data/data/Russian/Audio/rus_c1_151_kardinaln_y.mp3"
  },
  {
    "id": "rus_c1_152",
    "language_code": "ru",
    "level_tag": "C1_Vocabulary",
    "original_script": "Радикальный",
    "romanized_script": "Radikalnıy",
    "meaning": "Keskin çizgili / Radikal",
    "is_latin": false,
    "metadata": {
      "script_direction": "ltr"
    },
    "audioUrl": "/data/data/Russian/Audio/rus_c1_152_radikaln_y.mp3"
  },
  {
    "id": "rus_c1_153",
    "language_code": "ru",
    "level_tag": "C1_Vocabulary",
    "original_script": "Конструктивный",
    "romanized_script": "Konstruktivnıy",
    "meaning": "Çözüm odaklı / Yapıcı",
    "is_latin": false,
    "metadata": {
      "script_direction": "ltr"
    },
    "audioUrl": "/data/data/Russian/Audio/rus_c1_153_konstruktivn_y.mp3"
  },
  {
    "id": "rus_c1_154",
    "language_code": "ru",
    "level_tag": "C1_Vocabulary",
    "original_script": "Деструктивный",
    "romanized_script": "Destruktivnıy",
    "meaning": "Yıkıcı / Zarar veren mahiyette",
    "is_latin": false,
    "metadata": {
      "script_direction": "ltr"
    },
    "audioUrl": "/data/data/Russian/Audio/rus_c1_154_destruktivn_y.mp3"
  },
  {
    "id": "rus_c1_155",
    "language_code": "ru",
    "level_tag": "C1_Vocabulary",
    "original_script": "Легитимный",
    "romanized_script": "Legitimnıy",
    "meaning": "Hukuken meşru / Yasal tabanlı",
    "is_latin": false,
    "metadata": {
      "script_direction": "ltr"
    },
    "audioUrl": "/data/data/Russian/Audio/rus_c1_155_legitimn_y.mp3"
  },
  {
    "id": "rus_c1_156",
    "language_code": "ru",
    "level_tag": "C1_Vocabulary",
    "original_script": "Авторитетный",
    "romanized_script": "Avtoritetnıy",
    "meaning": "Sözü geçen / Saygın bilirkişi",
    "is_latin": false,
    "metadata": {
      "script_direction": "ltr"
    },
    "audioUrl": "/data/data/Russian/Audio/rus_c1_156_avtoritetn_y.mp3"
  },
  {
    "id": "rus_c1_157",
    "language_code": "ru",
    "level_tag": "C1_Vocabulary",
    "original_script": "Компетентный",
    "romanized_script": "Kompetentnıy",
    "meaning": "Donanımlı / Liyakatli / Yetkin",
    "is_latin": false,
    "metadata": {
      "script_direction": "ltr"
    },
    "audioUrl": "/data/data/Russian/Audio/rus_c1_157_kompetentn_y.mp3"
  },
  {
    "id": "rus_c1_158",
    "language_code": "ru",
    "level_tag": "C1_Vocabulary",
    "original_script": "Эквивалентный",
    "romanized_script": "Ekvivalentnıy",
    "meaning": "Eş değerlilik gösteren / Denk",
    "is_latin": false,
    "metadata": {
      "script_direction": "ltr"
    },
    "audioUrl": "/data/data/Russian/Audio/rus_c1_158_ekvivalentn_y.mp3"
  },
  {
    "id": "rus_c1_159",
    "language_code": "ru",
    "level_tag": "C1_Vocabulary",
    "original_script": "Прогрессивный",
    "romanized_script": "Progressivnıy",
    "meaning": "İleriyi hedefleyen / Yenilikçi",
    "is_latin": false,
    "metadata": {
      "script_direction": "ltr"
    },
    "audioUrl": "/data/data/Russian/Audio/rus_c1_159_progressivn_y.mp3"
  },
  {
    "id": "rus_c1_160",
    "language_code": "ru",
    "level_tag": "C1_Vocabulary",
    "original_script": "Консервативный",
    "romanized_script": "Konservativnıy",
    "meaning": "Gelenekçi / Statükocu",
    "is_latin": false,
    "metadata": {
      "script_direction": "ltr"
    },
    "audioUrl": "/data/data/Russian/Audio/rus_c1_160_konservativn_y.mp3"
  },
  {
    "id": "rus_c1_161",
    "language_code": "ru",
    "level_tag": "C1_Vocabulary",
    "original_script": "Следовательно",
    "romanized_script": "Sledovatelno",
    "meaning": "Çıkarım olarak / Dolayısıyla",
    "is_latin": false,
    "metadata": {
      "script_direction": "ltr"
    },
    "audioUrl": "/data/data/Russian/Audio/rus_c1_161_sledovatelno.mp3"
  },
  {
    "id": "rus_c1_162",
    "language_code": "ru",
    "level_tag": "C1_Vocabulary",
    "original_script": "Соответственно",
    "romanized_script": "Sootvetstvenno",
    "meaning": "Buna koşut olarak / Uygunca",
    "is_latin": false,
    "metadata": {
      "script_direction": "ltr"
    },
    "audioUrl": "/data/data/Russian/Audio/rus_c1_162_sootvetstvenno.mp3"
  },
  {
    "id": "rus_c1_163",
    "language_code": "ru",
    "level_tag": "C1_Vocabulary",
    "original_script": "В частности",
    "romanized_script": "V çastnosti",
    "meaning": "Tikel olarak / Hususiyetle",
    "is_latin": false,
    "metadata": {
      "script_direction": "ltr"
    },
    "audioUrl": "/data/data/Russian/Audio/rus_c1_163_v_astnosti.mp3"
  },
  {
    "id": "rus_c1_164",
    "language_code": "ru",
    "level_tag": "C1_Vocabulary",
    "original_script": "Взамен",
    "romanized_script": "Vzamen",
    "meaning": "İvaz olarak / İkame suretiyle",
    "is_latin": false,
    "metadata": {
      "script_direction": "ltr"
    },
    "audioUrl": "/data/data/Russian/Audio/rus_c1_164_vzamen.mp3"
  },
  {
    "id": "rus_c1_165",
    "language_code": "ru",
    "level_tag": "C1_Vocabulary",
    "original_script": "Ввиду того что",
    "romanized_script": "Vvidu togo çto",
    "meaning": "Gerekçesiyle / -den ötürü",
    "is_latin": false,
    "metadata": {
      "script_direction": "ltr"
    },
    "audioUrl": "/data/data/Russian/Audio/rus_c1_165_vvidu_togo_to.mp3"
  },
  {
    "id": "rus_c1_166",
    "language_code": "ru",
    "level_tag": "C1_Vocabulary",
    "original_script": "Несмотря на",
    "romanized_script": "Nesmotrya na",
    "meaning": "Fark gözetmeksizin / -e karşın",
    "is_latin": false,
    "metadata": {
      "script_direction": "ltr"
    },
    "audioUrl": "/data/data/Russian/Audio/rus_c1_166_nesmotrya_na.mp3"
  },
  {
    "id": "rus_c1_167",
    "language_code": "ru",
    "level_tag": "C1_Vocabulary",
    "original_script": "Вопреки",
    "romanized_script": "Vopreki",
    "meaning": "Hilafına / Mukabil olarak",
    "is_latin": false,
    "metadata": {
      "script_direction": "ltr"
    },
    "audioUrl": "/data/data/Russian/Audio/rus_c1_167_vopreki.mp3"
  },
  {
    "id": "rus_c1_168",
    "language_code": "ru",
    "level_tag": "C1_Vocabulary",
    "original_script": "Вследствие",
    "romanized_script": "Vsledstviye",
    "meaning": "Müsebbip olarak / Sonucunda",
    "is_latin": false,
    "metadata": {
      "script_direction": "ltr"
    },
    "audioUrl": "/data/data/Russian/Audio/rus_c1_168_vsledstviye.mp3"
  },
  {
    "id": "rus_c1_169",
    "language_code": "ru",
    "level_tag": "C1_Vocabulary",
    "original_script": "В силу этого",
    "romanized_script": "V silu etogo",
    "meaning": "Bu yasal dayanaktan ötürü",
    "is_latin": false,
    "metadata": {
      "script_direction": "ltr"
    },
    "audioUrl": "/data/data/Russian/Audio/rus_c1_169_v_silu_etogo.mp3"
  },
  {
    "id": "rus_c1_170",
    "language_code": "ru",
    "level_tag": "C1_Vocabulary",
    "original_script": "Преимущественно",
    "romanized_script": "Preimuşçestvenno",
    "meaning": "Kahir ekseriyetle / Ağırlıkça",
    "is_latin": false,
    "metadata": {
      "script_direction": "ltr"
    },
    "audioUrl": "/data/data/Russian/Audio/rus_c1_170_preimu_estvenno.mp3"
  },
  {
    "id": "rus_c1_171",
    "language_code": "ru",
    "level_tag": "C1_Vocabulary",
    "original_script": "Исключительно",
    "romanized_script": "Isklüçitelno",
    "meaning": "Münhasıran / Sadece ve sadece",
    "is_latin": false,
    "metadata": {
      "script_direction": "ltr"
    },
    "audioUrl": "/data/data/Russian/Audio/rus_c1_171_iskl_itelno.mp3"
  },
  {
    "id": "rus_c1_172",
    "language_code": "ru",
    "level_tag": "C1_Vocabulary",
    "original_script": "Относительно",
    "romanized_script": "Otnositelno",
    "meaning": "Nispeten / -e nispetle / Görece",
    "is_latin": false,
    "metadata": {
      "script_direction": "ltr"
    },
    "audioUrl": "/data/data/Russian/Audio/rus_c1_172_otnositelno.mp3"
  },
  {
    "id": "rus_c1_173",
    "language_code": "ru",
    "level_tag": "C1_Vocabulary",
    "original_script": "Приблизительно",
    "romanized_script": "Priblizitelno",
    "meaning": "Aşağı yukarı / Takriben",
    "is_latin": false,
    "metadata": {
      "script_direction": "ltr"
    },
    "audioUrl": "/data/data/Russian/Audio/rus_c1_173_priblizitelno.mp3"
  },
  {
    "id": "rus_c1_174",
    "language_code": "ru",
    "level_tag": "C1_Vocabulary",
    "original_script": "Фактически",
    "romanized_script": "Faktiçeski",
    "meaning": "De facto / Eylemsel olarak",
    "is_latin": false,
    "metadata": {
      "script_direction": "ltr"
    },
    "audioUrl": "/data/data/Russian/Audio/rus_c1_174_fakti_eski.mp3"
  },
  {
    "id": "rus_c1_175",
    "language_code": "ru",
    "level_tag": "C1_Vocabulary",
    "original_script": "Потенциально",
    "romanized_script": "Potentsialno",
    "meaning": "Gizil olarak / Potansiyelde",
    "is_latin": false,
    "metadata": {
      "script_direction": "ltr"
    },
    "audioUrl": "/data/data/Russian/Audio/rus_c1_175_potentsialno.mp3"
  },
  {
    "id": "rus_c1_176",
    "language_code": "ru",
    "level_tag": "C1_Vocabulary",
    "original_script": "Принципиально",
    "romanized_script": "Printsipialno",
    "meaning": "Prensip gereği / Esas yönünden",
    "is_latin": false,
    "metadata": {
      "script_direction": "ltr"
    },
    "audioUrl": "/data/data/Russian/Audio/rus_c1_176_printsipialno.mp3"
  },
  {
    "id": "rus_c1_177",
    "language_code": "ru",
    "level_tag": "C1_Vocabulary",
    "original_script": "Традиционно",
    "romanized_script": "Traditsionno",
    "meaning": "Gelenekselleşmiş biçimde",
    "is_latin": false,
    "metadata": {
      "script_direction": "ltr"
    },
    "audioUrl": "/data/data/Russian/Audio/rus_c1_177_traditsionno.mp3"
  },
  {
    "id": "rus_c1_178",
    "language_code": "ru",
    "level_tag": "C1_Vocabulary",
    "original_script": "Официально",
    "romanized_script": "Ofitsialno",
    "meaning": "Resmi kanallarca / Alenen",
    "is_latin": false,
    "metadata": {
      "script_direction": "ltr"
    },
    "audioUrl": "/data/data/Russian/Audio/rus_c1_178_ofitsialno.mp3"
  },
  {
    "id": "rus_c1_179",
    "language_code": "ru",
    "level_tag": "C1_Vocabulary",
    "original_script": "Практически",
    "romanized_script": "Praktiçeski",
    "meaning": "Neredeyse tamamen / Fiiliyatça",
    "is_latin": false,
    "metadata": {
      "script_direction": "ltr"
    },
    "audioUrl": "/data/data/Russian/Audio/rus_c1_179_prakti_eski.mp3"
  },
  {
    "id": "rus_c1_180",
    "language_code": "ru",
    "level_tag": "C1_Vocabulary",
    "original_script": "Теоретически",
    "romanized_script": "Teoretiçeski",
    "meaning": "Teoride / Varsayımsal düzlemde",
    "is_latin": false,
    "metadata": {
      "script_direction": "ltr"
    },
    "audioUrl": "/data/data/Russian/Audio/rus_c1_180_teoreti_eski.mp3"
  },
  {
    "id": "rus_c1_181",
    "language_code": "ru",
    "level_tag": "C1_Vocabulary",
    "original_script": "Индустриализация",
    "romanized_script": "Industrializatsiya",
    "meaning": "Sanayileşme süreci / Endüstrileşme",
    "is_latin": false,
    "metadata": {
      "script_direction": "ltr"
    },
    "audioUrl": "/data/data/Russian/Audio/rus_c1_181_industrializatsiya.mp3"
  },
  {
    "id": "rus_c1_182",
    "language_code": "ru",
    "level_tag": "C1_Vocabulary",
    "original_script": "Урбанизация",
    "romanized_script": "Urbanizatsiya",
    "meaning": "Kentleşme olgusu / Urbanizasyon",
    "is_latin": false,
    "metadata": {
      "script_direction": "ltr"
    },
    "audioUrl": "/data/data/Russian/Audio/rus_c1_182_urbanizatsiya.mp3"
  },
  {
    "id": "rus_c1_183",
    "language_code": "ru",
    "level_tag": "C1_Vocabulary",
    "original_script": "Глобализация",
    "romanized_script": "Globalizatsiya",
    "meaning": "Küreselleşme dalgası",
    "is_latin": false,
    "metadata": {
      "script_direction": "ltr"
    },
    "audioUrl": "/data/data/Russian/Audio/rus_c1_183_globalizatsiya.mp3"
  },
  {
    "id": "rus_c1_184",
    "language_code": "ru",
    "level_tag": "C1_Vocabulary",
    "original_script": "Демократизация",
    "romanized_script": "Demokratizatsiya",
    "meaning": "Demokratikleşme adımları",
    "is_latin": false,
    "metadata": {
      "script_direction": "ltr"
    },
    "audioUrl": "/data/data/Russian/Audio/rus_c1_184_demokratizatsiya.mp3"
  },
  {
    "id": "rus_c1_185",
    "language_code": "ru",
    "level_tag": "C1_Vocabulary",
    "original_script": "Национализация",
    "romanized_script": "Natsionalizatsiya",
    "meaning": "Devletleştirme / Kamulaştırma",
    "is_latin": false,
    "metadata": {
      "script_direction": "ltr"
    },
    "audioUrl": "/data/data/Russian/Audio/rus_c1_185_natsionalizatsiya.mp3"
  },
  {
    "id": "rus_c1_186",
    "language_code": "ru",
    "level_tag": "C1_Vocabulary",
    "original_script": "Приватизация",
    "romanized_script": "Privatizatsiya",
    "meaning": "Özeleştirme hamlesi",
    "is_latin": false,
    "metadata": {
      "script_direction": "ltr"
    },
    "audioUrl": "/data/data/Russian/Audio/rus_c1_186_privatizatsiya.mp3"
  },
  {
    "id": "rus_c1_187",
    "language_code": "ru",
    "level_tag": "C1_Vocabulary",
    "original_script": "Монополизация",
    "romanized_script": "Monopolizatsiya",
    "meaning": "Tekelleşme eğilimi",
    "is_latin": false,
    "metadata": {
      "script_direction": "ltr"
    },
    "audioUrl": "/data/data/Russian/Audio/rus_c1_187_monopolizatsiya.mp3"
  },
  {
    "id": "rus_c1_188",
    "language_code": "ru",
    "level_tag": "C1_Vocabulary",
    "original_script": "Централизация",
    "romanized_script": "Tsentralizatsiya",
    "meaning": "Merkezileştirme politikası",
    "is_latin": false,
    "metadata": {
      "script_direction": "ltr"
    },
    "audioUrl": "/data/data/Russian/Audio/rus_c1_188_tsentralizatsiya.mp3"
  },
  {
    "id": "rus_c1_189",
    "language_code": "ru",
    "level_tag": "C1_Vocabulary",
    "original_script": "Децентрализация",
    "romanized_script": "Detsentralizatsiya",
    "meaning": "Yerinden yönetim / Adem-i merkeziyet",
    "is_latin": false,
    "metadata": {
      "script_direction": "ltr"
    },
    "audioUrl": "/data/data/Russian/Audio/rus_c1_189_detsentralizatsiya.mp3"
  },
  {
    "id": "rus_c1_190",
    "language_code": "ru",
    "level_tag": "C1_Vocabulary",
    "original_script": "Бюрократизация",
    "romanized_script": "Byurokratizatsiya",
    "meaning": "Kırtasiyecilik / Bürokratikleşme",
    "is_latin": false,
    "metadata": {
      "script_direction": "ltr"
    },
    "audioUrl": "/data/data/Russian/Audio/rus_c1_190_byurokratizatsiya.mp3"
  },
  {
    "id": "rus_c1_191",
    "language_code": "ru",
    "level_tag": "C1_Vocabulary",
    "original_script": "Интегрированный",
    "romanized_script": "Integrirovannıy",
    "meaning": "Bütünleşik / Entegre edilmiş",
    "is_latin": false,
    "metadata": {
      "script_direction": "ltr"
    },
    "audioUrl": "/data/data/Russian/Audio/rus_c1_191_integrirovann_y.mp3"
  },
  {
    "id": "rus_c1_192",
    "language_code": "ru",
    "level_tag": "C1_Vocabulary",
    "original_script": "Дифференцированный",
    "romanized_script": "Differentsirovannıy",
    "meaning": "Kademeli / Özelleştirilmiş / Ayrışmış",
    "is_latin": false,
    "metadata": {
      "script_direction": "ltr"
    },
    "audioUrl": "/data/data/Russian/Audio/rus_c1_192_differentsirovann_y.mp3"
  },
  {
    "id": "rus_c1_193",
    "language_code": "ru",
    "level_tag": "C1_Vocabulary",
    "original_script": "Трансформированный",
    "romanized_script": "Transformirovannıy",
    "meaning": "Başkalaşmış / Dönüştürülmüş",
    "is_latin": false,
    "metadata": {
      "script_direction": "ltr"
    },
    "audioUrl": "/data/data/Russian/Audio/rus_c1_193_transformirovann_y.mp3"
  },
  {
    "id": "rus_c1_194",
    "language_code": "ru",
    "level_tag": "C1_Vocabulary",
    "original_script": "Регулируемый",
    "romanized_script": "Reguliruyemıy",
    "meaning": "Denetim altında tutulan / Güdümlü",
    "is_latin": false,
    "metadata": {
      "script_direction": "ltr"
    },
    "audioUrl": "/data/data/Russian/Audio/rus_c1_194_reguliruyem_y.mp3"
  },
  {
    "id": "rus_c1_195",
    "language_code": "ru",
    "level_tag": "C1_Vocabulary",
    "original_script": "Контролируемый",
    "romanized_script": "Kontroliruyemıy",
    "meaning": "Kontrollü / Kontrol edilen",
    "is_latin": false,
    "metadata": {
      "script_direction": "ltr"
    },
    "audioUrl": "/data/data/Russian/Audio/rus_c1_195_kontroliruyem_y.mp3"
  },
  {
    "id": "rus_c1_196",
    "language_code": "ru",
    "level_tag": "C1_Vocabulary",
    "original_script": "Прогнозируемый",
    "romanized_script": "Prognoziruyemıy",
    "meaning": "Kestirilebilir / Öngörülebilir",
    "is_latin": false,
    "metadata": {
      "script_direction": "ltr"
    },
    "audioUrl": "/data/data/Russian/Audio/rus_c1_196_prognoziruyem_y.mp3"
  },
  {
    "id": "rus_c1_197",
    "language_code": "ru",
    "level_tag": "C1_Vocabulary",
    "original_script": "Обоснованный",
    "romanized_script": "Obosnovannıy",
    "meaning": "Meselede haklı / Gerekçeli / Meşru",
    "is_latin": false,
    "metadata": {
      "script_direction": "ltr"
    },
    "audioUrl": "/data/data/Russian/Audio/rus_c1_197_obosnovann_y.mp3"
  },
  {
    "id": "rus_c1_198",
    "language_code": "ru",
    "level_tag": "C1_Vocabulary",
    "original_script": "Доказанный",
    "romanized_script": "Dokazannıy",
    "meaning": "Hükmen sabit / İspatlanmış",
    "is_latin": false,
    "metadata": {
      "script_direction": "ltr"
    },
    "audioUrl": "/data/data/Russian/Audio/rus_c1_198_dokazann_y.mp3"
  },
  {
    "id": "rus_c1_199",
    "language_code": "ru",
    "level_tag": "C1_Vocabulary",
    "original_script": "Опровергнутый",
    "romanized_script": "Oprovergnutıy",
    "meaning": "Çürütülmüş / Geçersiz kılınmış",
    "is_latin": false,
    "metadata": {
      "script_direction": "ltr"
    },
    "audioUrl": "/data/data/Russian/Audio/rus_c1_199_oprovergnut_y.mp3"
  },
  {
    "id": "rus_c1_200",
    "language_code": "ru",
    "level_tag": "C1_Vocabulary",
    "original_script": "Фундаментальный",
    "romanized_script": "Fundamentalnıy",
    "meaning": "Köksel / Esaslı / Temel nitelikteki",
    "is_latin": false,
    "metadata": {
      "script_direction": "ltr"
    },
    "audioUrl": "/data/data/Russian/Audio/rus_c1_200_fundamentaln_y.mp3"
  }
]