{
  "sector_meta": {
    "language_pair": "en_tr_phrases",
    "theme": "Summer Vacation Essential Phrases / Yaz Tatili Temel Cümleleri",
    "total_phrases": 100
  },
  "phrase_vault": [
    {
      "id": "phr_sum_et_001",
      "mission_phrase": "Can I have an ice cream, please?",
      "target_translation": "Bir dondurma alabilir miyim, lütfen?",
      "clue_text": "Külah veya kapta soğuk lezzet isterken",
      "shells_pool": [
        "Bir dondurma alabilir miyim, lütfen?",
        "Hadi kumdan kale yapalım!",
        "Deniz bugün çok güzel.",
        "Güneş kremim nerede?"
      ]
    },
    {
      "id": "phr_sum_et_002",
      "mission_phrase": "Let's build a sandcastle!",
      "target_translation": "Hadi kumdan kale yapalım!",
      "clue_text": "Sahilde kova ve kürekle oynayalım derken",
      "shells_pool": [
        "Hadi kumdan kale yapalım!",
        "Bir dondurma alabilir miyim, lütfen?",
        "Deniz bugün çok güzel.",
        "Güneş kremim nerede?"
      ]
    },
    {
      "id": "phr_sum_et_003",
      "mission_phrase": "The sea is very beautiful today.",
      "target_translation": "Deniz bugün çok güzel.",
      "clue_text": "Mavi suların harika göründüğünü söylerken",
      "shells_pool": [
        "Deniz bugün çok güzel.",
        "Bir dondurma alabilir miyim, lütfen?",
        "Hadi kumdan kale yapalım!",
        "Güneş kremim nerede?"
      ]
    },
    {
      "id": "phr_sum_et_004",
      "mission_phrase": "Where is my sunscreen?",
      "target_translation": "Güneş kremim nerede?",
      "clue_text": "Güneşte yanmamak için sürülen losyonu ararken",
      "shells_pool": [
        "Güneş kremim nerede?",
        "Bir dondurma alabilir miyim, lütfen?",
        "Hadi kumdan kale yapalım!",
        "Deniz bugün çok güzel."
      ]
    },
    {
      "id": "phr_sum_et_005",
      "mission_phrase": "I want to swim in the pool.",
      "target_translation": "Havuzda yüzmek istiyorum.",
      "clue_text": "Yapay tatlı su alanına girmek isterken",
      "shells_pool": [
        "Havuzda yüzmek istiyorum.",
        "Bir dondurma alabilir miyim, lütfen?",
        "Hadi kumdan kale yapalım!",
        "Deniz bugün çok güzel."
      ]
    },
    {
      "id": "phr_sum_et_006",
      "mission_phrase": "Can we go to the beach?",
      "target_translation": "Plaja gidebilir miyiz?",
      "clue_text": "Deniz kenarına, kumlara gitmeyi teklif ederken",
      "shells_pool": [
        "Plaja gidebilir miyiz?",
        "Bir dondurma alabilir miyim, lütfen?",
        "Hadi kumdan kale yapalım!",
        "Deniz bugün çok güzel."
      ]
    },
    {
      "id": "phr_sum_et_007",
      "mission_phrase": "Look at that big wave!",
      "target_translation": "Şu büyük dalgaya bak!",
      "clue_text": "Denizde yükselen su kütlesini gösterirken",
      "shells_pool": [
        "Şu büyük dalgaya bak!",
        "Bir dondurma alabilir miyim, lütfen?",
        "Hadi kumdan kale yapalım!",
        "Deniz bugün çok güzel."
      ]
    },
    {
      "id": "phr_sum_et_008",
      "mission_phrase": "I found a beautiful seashell.",
      "target_translation": "Güzel bir deniz kabuğu buldum.",
      "clue_text": "Kumsalda yürürken toplanan sert kabuğu gösterirken",
      "shells_pool": [
        "Güzel bir deniz kabuğu buldum.",
        "Bir dondurma alabilir miyim, lütfen?",
        "Hadi kumdan kale yapalım!",
        "Deniz bugün çok güzel."
      ]
    },
    {
      "id": "phr_sum_et_009",
      "mission_phrase": "Don't forget your sunglasses.",
      "target_translation": "Güneş gözlüğünü unutma.",
      "clue_text": "Gözleri koruyan renkli camlı aksesuarı hatırlatırken",
      "shells_pool": [
        "Güneş gözlüğünü unutma.",
        "Bir dondurma alabilir miyim, lütfen?",
        "Hadi kumdan kale yapalım!",
        "Deniz bugün çok güzel."
      ]
    },
    {
      "id": "phr_sum_et_010",
      "mission_phrase": "Where are my flip-flops?",
      "target_translation": "Parmak arası terliklerim nerede?",
      "clue_text": "Plajda veya bahçede giyilen açık pabucu ararken",
      "shells_pool": [
        "Parmak arası terliklerim nerede?",
        "Bir dondurma alabilir miyim, lütfen?",
        "Hadi kumdan kale yapalım!",
        "Deniz bugün çok güzel."
      ]
    },
    {
      "id": "phr_sum_et_011",
      "mission_phrase": "I am putting on my hat.",
      "target_translation": "Şapkamı takıyorum.",
      "clue_text": "Başı güneşten korumak için yapılan eylem",
      "shells_pool": [
        "Şapkamı takıyorum.",
        "Bir dondurma alabilir miyim, lütfen?",
        "Hadi kumdan kale yapalım!",
        "Deniz bugün çok güzel."
      ]
    },
    {
      "id": "phr_sum_et_012",
      "mission_phrase": "Is the water cold or warm?",
      "target_translation": "Su soğuk mu yoksa ılık mı?",
      "clue_text": "Denize girmeden önce sıcaklığı merak ederken",
      "shells_pool": [
        "Su soğuk mu yoksa ılık mı?",
        "Bir dondurma alabilir miyim, lütfen?",
        "Hadi kumdan kale yapalım!",
        "Deniz bugün çok güzel."
      ]
    },
    {
      "id": "phr_sum_et_013",
      "mission_phrase": "I want to drink lemonade.",
      "target_translation": "Limonata içmek istiyorum.",
      "clue_text": "Yazın serinletici, ekşi ve tatlı sarı içeceği isterken",
      "shells_pool": [
        "Limonata içmek istiyorum.",
        "Bir dondurma alabilir miyim, lütfen?",
        "Hadi kumdan kale yapalım!",
        "Deniz bugün çok güzel."
      ]
    },
    {
      "id": "phr_sum_et_014",
      "mission_phrase": "Let's play with the beach ball.",
      "target_translation": "Plaj topuyla oynayalım.",
      "clue_text": "Kumsalda şişme yuvarlak oyuncakla oynama daveti",
      "shells_pool": [
        "Plaj topuyla oynayalım.",
        "Bir dondurma alabilir miyim, lütfen?",
        "Hadi kumdan kale yapalım!",
        "Deniz bugün çok güzel."
      ]
    },
    {
      "id": "phr_sum_et_015",
      "mission_phrase": "Can I have a slice of watermelon?",
      "target_translation": "Bir dilim karpuz alabilir miyim?",
      "clue_text": "Yazın içi kırmızı sulu meyvesini isterken",
      "shells_pool": [
        "Bir dilim karpuz alabilir miyim?",
        "Bir dondurma alabilir miyim, lütfen?",
        "Hadi kumdan kale yapalım!",
        "Deniz bugün çok güzel."
      ]
    },
    {
      "id": "phr_sum_et_016",
      "mission_phrase": "We are going on vacation tomorrow.",
      "target_translation": "Yarın tatile gidiyoruz.",
      "clue_text": "Yolculuktan bir gün önceki büyük heyecan cümlesi",
      "shells_pool": [
        "Yarın tatile gidiyoruz.",
        "Bir dondurma alabilir miyim, lütfen?",
        "Hadi kumdan kale yapalım!",
        "Deniz bugün çok güzel."
      ]
    },
    {
      "id": "phr_sum_et_017",
      "mission_phrase": "Help me pack my suitcase, please.",
      "target_translation": "Valizimi toplamama yardım et, lütfen.",
      "clue_text": "Bavula kıyafetleri yerleştirirken yardım isterken",
      "shells_pool": [
        "Valizimi toplamama yardım et, lütfen.",
        "Bir dondurma alabilir miyim, lütfen?",
        "Hadi kumdan kale yapalım!",
        "Deniz bugün çok güzel."
      ]
    },
    {
      "id": "phr_sum_et_018",
      "mission_phrase": "Where is the hotel lobby?",
      "target_translation": "Otel lobisi nerede?",
      "clue_text": "Otele ilk girişte resepsiyonun olduğu alanı sorarken",
      "shells_pool": [
        "Otel lobisi nerede?",
        "Bir dondurma alabilir miyim, lütfen?",
        "Hadi kumdan kale yapalım!",
        "Deniz bugün çok güzel."
      ]
    },
    {
      "id": "phr_sum_et_019",
      "mission_phrase": "I love riding my bicycle in summer.",
      "target_translation": "Yazın bisiklete binmeyi çok seviyorum.",
      "clue_text": "İki tekerlekli pedallı aracı sürme keyfini anlatırken",
      "shells_pool": [
        "Yazın bisiklete binmeyi çok seviyorum.",
        "Bir dondurma alabilir miyim, lütfen?",
        "Hadi kumdan kale yapalım!",
        "Deniz bugün çok güzel."
      ]
    },
    {
      "id": "phr_sum_et_020",
      "mission_phrase": "Let's fly a kite in the park.",
      "target_translation": "Parkta uçurtma uçuralım.",
      "clue_text": "Rüzgarlı havada ipli kağıt oyuncağı göğe salma teklifi",
      "shells_pool": [
        "Parkta uçurtma uçuralım.",
        "Bir dondurma alabilir miyim, lütfen?",
        "Hadi kumdan kale yapalım!",
        "Deniz bugün çok güzel."
      ]
    },
    {
      "id": "phr_sum_et_021",
      "mission_phrase": "Can we take a photo here?",
      "target_translation": "Burada fotoğraf çekilebilir miyiz?",
      "clue_text": "Güzel bir manzarada anı kaydetmek isterken",
      "shells_pool": [
        "Burada fotoğraf çekilebilir miyiz?",
        "Bir dondurma alabilir miyim, lütfen?",
        "Hadi kumdan kale yapalım!",
        "Deniz bugün çok güzel."
      ]
    },
    {
      "id": "phr_sum_et_022",
      "mission_phrase": "I am ready for the summer camp.",
      "target_translation": "Yaz kampı için hazırım.",
      "clue_text": "Doğada çadır kurup kalma etkinliğine hazırken",
      "shells_pool": [
        "Yaz kampı için hazırım.",
        "Bir dondurma alabilir miyim, lütfen?",
        "Hadi kumdan kale yapalım!",
        "Deniz bugün çok güzel."
      ]
    },
    {
      "id": "phr_sum_et_023",
      "mission_phrase": "Let's set up the tent here.",
      "target_translation": "Çadırı buraya kuralım.",
      "clue_text": "Kamp alanında taşınabilir kumaş evi kurma yeri seçerken",
      "shells_pool": [
        "Çadırı buraya kuralım.",
        "Bir dondurma alabilir miyim, lütfen?",
        "Hadi kumdan kale yapalım!",
        "Deniz bugün çok güzel."
      ]
    },
    {
      "id": "phr_sum_et_024",
      "mission_phrase": "We had a picnic in the forest.",
      "target_translation": "Ormanda piknik yaptık.",
      "clue_text": "Ağaçlık alanda sepetle yemek yendiğini anlatırken",
      "shells_pool": [
        "Ormanda piknik yaptık.",
        "Bir dondurma alabilir miyim, lütfen?",
        "Hadi kumdan kale yapalım!",
        "Deniz bugün çok güzel."
      ]
    },
    {
      "id": "phr_sum_et_025",
      "mission_phrase": "Can I dive into the water?",
      "target_translation": "Suya dalabilir miyim?",
      "clue_text": "Suyun altına, derinlere inmek için izin isterken",
      "shells_pool": [
        "Suya dalabilir miyim?",
        "Bir dondurma alabilir miyim, lütfen?",
        "Hadi kumdan kale yapalım!",
        "Deniz bugün çok güzel."
      ]
    },
    {
      "id": "phr_sum_et_026",
      "mission_phrase": "Look, a dolphin is jumping!",
      "target_translation": "Bak, bir yunus zıplıyor!",
      "clue_text": "Denizdeki sevimli ve akıllı memeli canlıyı görünce",
      "shells_pool": [
        "Bak, bir yunus zıplıyor!",
        "Bir dondurma alabilir miyim, lütfen?",
        "Hadi kumdan kale yapalım!",
        "Deniz bugün çok güzel."
      ]
    },
    {
      "id": "phr_sum_et_027",
      "mission_phrase": "The seagulls are very loud.",
      "target_translation": "Martılar çok gürültülü.",
      "clue_text": "Deniz kenarında simit isteyen beyaz kuşların sesini duyunca",
      "shells_pool": [
        "Martılar çok gürültülü.",
        "Bir dondurma alabilir miyim, lütfen?",
        "Hadi kumdan kale yapalım!",
        "Deniz bugün çok güzel."
      ]
    },
    {
      "id": "phr_sum_et_028",
      "mission_phrase": "I need my swimming goggles.",
      "target_translation": "Deniz gözlüğüme ihtiyacım var.",
      "clue_text": "Suda gözleri açıp altı net görmek için kullanılan aracı isterken",
      "shells_pool": [
        "Deniz gözlüğüme ihtiyacım var.",
        "Bir dondurma alabilir miyim, lütfen?",
        "Hadi kumdan kale yapalım!",
        "Deniz bugün çok güzel."
      ]
    },
    {
      "id": "phr_sum_et_029",
      "mission_phrase": "Let's sit in the shade.",
      "target_translation": "Gölgede oturalım.",
      "clue_text": "Güneşten kaçıp serin bir ağaç veya şemsiye altı ararken",
      "shells_pool": [
        "Gölgede oturalım.",
        "Bir dondurma alabilir miyim, lütfen?",
        "Hadi kumdan kale yapalım!",
        "Deniz bugün çok güzel."
      ]
    },
    {
      "id": "phr_sum_et_030",
      "mission_phrase": "Open the beach umbrella, please.",
      "target_translation": "Plaj şemsiyesini aç, lütfen.",
      "clue_text": "Sahilde büyük tentyi kurmasını rica ederken",
      "shells_pool": [
        "Plaj şemsiyesini aç, lütfen.",
        "Bir dondurma alabilir miyim, lütfen?",
        "Hadi kumdan kale yapalım!",
        "Deniz bugün çok güzel."
      ]
    },
    {
      "id": "phr_sum_et_031",
      "mission_phrase": "Put some ice in my juice.",
      "target_translation": "Meyve suyuma biraz buz koy.",
      "clue_text": "İçeceği daha soğuk hale getirmek isterken",
      "shells_pool": [
        "Meyve suyuma biraz buz koy.",
        "Bir dondurma alabilir miyim, lütfen?",
        "Hadi kumdan kale yapalım!",
        "Deniz bugün çok güzel."
      ]
    },
    {
      "id": "phr_sum_et_032",
      "mission_phrase": "I want to watch the sunset.",
      "target_translation": "Güneşin batışını izlemek istiyorum.",
      "clue_text": "Akşamüstü gökyüzünün kızarmasını seyretme isteği",
      "shells_pool": [
        "Güneşin batışını izlemek istiyorum.",
        "Bir dondurma alabilir miyim, lütfen?",
        "Hadi kumdan kale yapalım!",
        "Deniz bugün çok güzel."
      ]
    },
    {
      "id": "phr_sum_et_033",
      "mission_phrase": "We are going to an island by boat.",
      "target_translation": "Tekneyle bir adaya gidiyoruz.",
      "clue_text": "Deniz yoluyla etrafı sularla çevrili karaya giderken",
      "shells_pool": [
        "Tekneyle bir adaya gidiyoruz.",
        "Bir dondurma alabilir miyim, lütfen?",
        "Hadi kumdan kale yapalım!",
        "Deniz bugün çok güzel."
      ]
    },
    {
      "id": "phr_sum_et_034",
      "mission_phrase": "Can you give me a towel?",
      "target_translation": "Bana bir havlu verebilir misin?",
      "clue_text": "Denizden çıkıp kurulanmak için kumaş isterken",
      "shells_pool": [
        "Bana bir havlu verebilir misin?",
        "Bir dondurma alabilir miyim, lütfen?",
        "Hadi kumdan kale yapalım!",
        "Deniz bugün çok güzel."
      ]
    },
    {
      "id": "phr_sum_et_035",
      "mission_phrase": "I am floating on the water.",
      "target_translation": "Suyun üstünde batmadan duruyorum.",
      "clue_text": "Deniz yatağında veya sırtüstü dengede kalırken",
      "shells_pool": [
        "Suyun üstünde batmadan duruyorum.",
        "Bir dondurma alabilir miyim, lütfen?",
        "Hadi kumdan kale yapalım!",
        "Deniz bugün çok güzel."
      ]
    },
    {
      "id": "phr_sum_et_036",
      "mission_phrase": "Watch out for the little crab!",
      "target_translation": "Küçük yengece dikkat et!",
      "clue_text": "Sahilde yan yan yürüyen kıskaçı hayvana karşı uyarırken",
      "shells_pool": [
        "Küçük yengece dikkat et!",
        "Bir dondurma alabilir miyim, lütfen?",
        "Hadi kumdan kale yapalım!",
        "Deniz bugün çok güzel."
      ]
    },
    {
      "id": "phr_sum_et_037",
      "mission_phrase": "I want to collect seashells.",
      "target_translation": "Deniz kabuğu toplamak istiyorum.",
      "clue_text": "Sahil boyunca yürüyüp kabuk arama isteği",
      "shells_pool": [
        "Deniz kabuğu toplamak istiyorum.",
        "Bir dondurma alabilir miyim, lütfen?",
        "Hadi kumdan kale yapalım!",
        "Deniz bugün çok güzel."
      ]
    },
    {
      "id": "phr_sum_et_038",
      "mission_phrase": "Let's go for a walk on the beach.",
      "target_translation": "Sahilde yürüyüşe çıkalım.",
      "clue_text": "Akşamüstü kumsalda yavaş adımlarla ilerleme daveti",
      "shells_pool": [
        "Sahilde yürüyüşe çıkalım.",
        "Bir dondurma alabilir miyim, lütfen?",
        "Hadi kumdan kale yapalım!",
        "Deniz bugün çok güzel."
      ]
    },
    {
      "id": "phr_sum_et_039",
      "mission_phrase": "The sun is shining brightly.",
      "target_translation": "Güneş çok parlak parlıyor.",
      "clue_text": "Gökyüzünün tamamen açık ve ışıklı olduğunu söylerken",
      "shells_pool": [
        "Güneş çok parlak parlıyor.",
        "Bir dondurma alabilir miyim, lütfen?",
        "Hadi kumdan kale yapalım!",
        "Deniz bugün çok güzel."
      ]
    },
    {
      "id": "phr_sum_et_040",
      "mission_phrase": "I feel very happy today.",
      "target_translation": "Bugün çok mutlu hissediyorum.",
      "clue_text": "Tatilde keyfinin yerinde olduğunu anlatırken",
      "shells_pool": [
        "Bugün çok mutlu hissediyorum.",
        "Bir dondurma alabilir miyim, lütfen?",
        "Hadi kumdan kale yapalım!",
        "Deniz bugün çok güzel."
      ]
    },
    {
      "id": "phr_sum_et_041",
      "mission_phrase": "Can we go to the aqua park?",
      "target_translation": "Su parkına gidebilir miyiz?",
      "clue_text": "Büyük kaydıraklı havuz eğlence merkezini isterken",
      "shells_pool": [
        "Su parkına gidebilir miyiz?",
        "Bir dondurma alabilir miyim, lütfen?",
        "Hadi kumdan kale yapalım!",
        "Deniz bugün çok güzel."
      ]
    },
    {
      "id": "phr_sum_et_042",
      "mission_phrase": "Where is my passport?",
      "target_translation": "Pasaportum nerede?",
      "clue_text": "Yurt dışı uçuşu öncesi resmi kimlik defterini ararken",
      "shells_pool": [
        "Pasaportum nerede?",
        "Bir dondurma alabilir miyim, lütfen?",
        "Hadi kumdan kale yapalım!",
        "Deniz bugün çok güzel."
      ]
    },
    {
      "id": "phr_sum_et_043",
      "mission_phrase": "The train is leaving now.",
      "target_translation": "Tren şimdi kalkıyor.",
      "clue_text": "Raylar üzerindeki vagonlu taşıt hareket ederken",
      "shells_pool": [
        "Tren şimdi kalkıyor.",
        "Bir dondurma alabilir miyim, lütfen?",
        "Hadi kumdan kale yapalım!",
        "Deniz bugün çok güzel."
      ]
    },
    {
      "id": "phr_sum_et_044",
      "mission_phrase": "I have two tickets for the ferry.",
      "target_translation": "Feribot için iki biletim var.",
      "clue_text": "Arabaları da taşıyan büyük deniz motorunun kartını gösterirken",
      "shells_pool": [
        "Feribot için iki biletim var.",
        "Bir dondurma alabilir miyim, lütfen?",
        "Hadi kumdan kale yapalım!",
        "Deniz bugün çok güzel."
      ]
    },
    {
      "id": "phr_sum_et_045",
      "mission_phrase": "Let's play a video game.",
      "target_translation": "Hadi bir video oyunu oynayalım.",
      "clue_text": "Telefon veya konsolda dijital eğlence daveti",
      "shells_pool": [
        "Hadi bir video oyunu oynayalım.",
        "Bir dondurma alabilir miyim, lütfen?",
        "Hadi kumdan kale yapalım!",
        "Deniz bugün çok güzel."
      ]
    },
    {
      "id": "phr_sum_et_046",
      "mission_phrase": "I made a new friend today.",
      "target_translation": "Bugün yeni bir arkadaş edindim.",
      "clue_text": "Otelde veya parkta tanışılan yeni dostu anlatırken",
      "shells_pool": [
        "Bugün yeni bir arkadaş edindim.",
        "Bir dondurma alabilir miyim, lütfen?",
        "Hadi kumdan kale yapalım!",
        "Deniz bugün çok güzel."
      ]
    },
    {
      "id": "phr_sum_et_047",
      "mission_phrase": "Can I play with your ball?",
      "target_translation": "Topunla oynayabilir miyim?",
      "clue_text": "Başka bir çocuğun yuvarlak oyuncağını isterken",
      "shells_pool": [
        "Topunla oynayabilir miyim?",
        "Bir dondurma alabilir miyim, lütfen?",
        "Hadi kumdan kale yapalım!",
        "Deniz bugün çok güzel."
      ]
    },
    {
      "id": "phr_sum_et_048",
      "mission_phrase": "This summer is wonderful.",
      "target_translation": "Bu yaz harika.",
      "clue_text": "Tatilin mükemmel geçtiğini genel olarak anlatırken",
      "shells_pool": [
        "Bu yaz harika.",
        "Bir dondurma alabilir miyim, lütfen?",
        "Hadi kumdan kale yapalım!",
        "Deniz bugün çok güzel."
      ]
    },
    {
      "id": "phr_sum_et_049",
      "mission_phrase": "I am reading a summer book.",
      "target_translation": "Bir yaz kitabı okuyorum.",
      "clue_text": "Ağaç gölgesinde veya şezlongda hikaye okurken",
      "shells_pool": [
        "Bir yaz kitabı okuyorum.",
        "Bir dondurma alabilir miyim, lütfen?",
        "Hadi kumdan kale yapalım!",
        "Deniz bugün çok güzel."
      ]
    },
    {
      "id": "phr_sum_et_050",
      "mission_phrase": "Where can we rent a bicycle?",
      "target_translation": "Nereden bisiklet kiralayabiliriz?",
      "clue_text": "Sahilde turlamak için pedallı araç ararken",
      "shells_pool": [
        "Nereden bisiklet kiralayabiliriz?",
        "Bir dondurma alabilir miyim, lütfen?",
        "Hadi kumdan kale yapalım!",
        "Deniz bugün çok güzel."
      ]
    },
    {
      "id": "phr_sum_et_051",
      "mission_phrase": "I like the summer breeze.",
      "target_translation": "Yaz esintisini seviyorum.",
      "clue_text": "Akşamüstü yüze vuran hafif ferahlatıcı rüzgarı överken",
      "shells_pool": [
        "Yaz esintisini seviyorum.",
        "Bir dondurma alabilir miyim, lütfen?",
        "Hadi kumdan kale yapalım!",
        "Deniz bugün çok güzel."
      ]
    },
    {
      "id": "phr_sum_et_052",
      "mission_phrase": "Let's buy some souvenirs.",
      "target_translation": "Biraz hediyelik eşya satın alalım.",
      "clue_text": "Tatile gidilen yerden arkadaşlara anı eşyası seçerken",
      "shells_pool": [
        "Biraz hediyelik eşya satın alalım.",
        "Bir dondurma alabilir miyim, lütfen?",
        "Hadi kumdan kale yapalım!",
        "Deniz bugün çok güzel."
      ]
    },
    {
      "id": "phr_sum_et_053",
      "mission_phrase": "My room has a sea view.",
      "target_translation": "Odam deniz manzaralı.",
      "clue_text": "Otel odasının penceresinden mavi sular görünürken",
      "shells_pool": [
        "Odam deniz manzaralı.",
        "Bir dondurma alabilir miyim, lütfen?",
        "Hadi kumdan kale yapalım!",
        "Deniz bugün çok güzel."
      ]
    },
    {
      "id": "phr_sum_et_054",
      "mission_phrase": "Can I have some cold water?",
      "target_translation": "Biraz soğuk su alabilir miyim?",
      "clue_text": "Çok sıcaklayıp serinletici saf sıvı isterken",
      "shells_pool": [
        "Biraz soğuk su alabilir miyim?",
        "Bir dondurma alabilir miyim, lütfen?",
        "Hadi kumdan kale yapalım!",
        "Deniz bugün çok güzel."
      ]
    },
    {
      "id": "phr_sum_et_055",
      "mission_phrase": "The pool is very crowded.",
      "target_translation": "Havuz çok kalabalık.",
      "clue_text": "Yüzme alanında çok fazla insan olduğunu görünce",
      "shells_pool": [
        "Havuz çok kalabalık.",
        "Bir dondurma alabilir miyim, lütfen?",
        "Hadi kumdan kale yapalım!",
        "Deniz bugün çok güzel."
      ]
    },
    {
      "id": "phr_sum_et_056",
      "mission_phrase": "Let's wake up early tomorrow.",
      "target_translation": "Yarın erken uyanalım.",
      "clue_text": "Sabah tatil gününü kaçırmamak için plan yaparken",
      "shells_pool": [
        "Yarın erken uyanalım.",
        "Bir dondurma alabilir miyim, lütfen?",
        "Hadi kumdan kale yapalım!",
        "Deniz bugün çok güzel."
      ]
    },
    {
      "id": "phr_sum_et_057",
      "mission_phrase": "I want to see the stars.",
      "target_translation": "Yıldızları görmek istiyorum.",
      "clue_text": "Gece gökyüzündeki parıldayan gök cisimlerine bakarken",
      "shells_pool": [
        "Yıldızları görmek istiyorum.",
        "Bir dondurma alabilir miyim, lütfen?",
        "Hadi kumdan kale yapalım!",
        "Deniz bugün çok güzel."
      ]
    },
    {
      "id": "phr_sum_et_058",
      "mission_phrase": "The moon is full tonight.",
      "target_translation": "Bu gece dolunay var.",
      "clue_text": "Gökyüzünde ayın tamamen yuvarlak ve parlak halini görünce",
      "shells_pool": [
        "Bu gece dolunay var.",
        "Bir dondurma alabilir miyim, lütfen?",
        "Hadi kumdan kale yapalım!",
        "Deniz bugün çok güzel."
      ]
    },
    {
      "id": "phr_sum_et_059",
      "mission_phrase": "Where is the nearest theme park?",
      "target_translation": "En yakın eğlence parkı nerede?",
      "clue_text": "Lunapark veya büyük oyuncaklı parkı ararken",
      "shells_pool": [
        "En yakın eğlence parkı nerede?",
        "Bir dondurma alabilir miyim, lütfen?",
        "Hadi kumdan kale yapalım!",
        "Deniz bugün çok güzel."
      ]
    },
    {
      "id": "phr_sum_et_060",
      "mission_phrase": "I am eating a sweet peach.",
      "target_translation": "Tatlı bir şeftali yiyorum.",
      "clue_text": "Yazın tüylü ve sulu meyvesini tüketirken",
      "shells_pool": [
        "Tatlı bir şeftali yiyorum.",
        "Bir dondurma alabilir miyim, lütfen?",
        "Hadi kumdan kale yapalım!",
        "Deniz bugün çok güzel."
      ]
    },
    {
      "id": "phr_sum_et_061",
      "mission_phrase": "Can we go fishing?",
      "target_translation": "Balık tutmaya gidebilir miyiz?",
      "clue_text": "Olta alıp deniz veya nehir kenarına gitme ricası",
      "shells_pool": [
        "Balık tutmaya gidebilir miyiz?",
        "Bir dondurma alabilir miyim, lütfen?",
        "Hadi kumdan kale yapalım!",
        "Deniz bugün çok güzel."
      ]
    },
    {
      "id": "phr_sum_et_062",
      "mission_phrase": "The sand is too hot.",
      "target_translation": "Kum çok sıcak.",
      "clue_text": "Öğlen vakti kumsalda ayağı yanarken söylenen cümle",
      "shells_pool": [
        "Kum çok sıcak.",
        "Bir dondurma alabilir miyim, lütfen?",
        "Hadi kumdan kale yapalım!",
        "Deniz bugün çok güzel."
      ]
    },
    {
      "id": "phr_sum_et_063",
      "mission_phrase": "I lost my room key.",
      "target_translation": "Oda anahtarımı kaybettim.",
      "clue_text": "Otel odasının kapısında kalıp resepsiyona giderken",
      "shells_pool": [
        "Oda anahtarımı kaybettim.",
        "Bir dondurma alabilir miyim, lütfen?",
        "Hadi kumdan kale yapalım!",
        "Deniz bugün çok güzel."
      ]
    },
    {
      "id": "phr_sum_et_064",
      "mission_phrase": "Let's listen to the waves.",
      "target_translation": "Dalgaları dinleyelim.",
      "clue_text": "Sahilde sessizce deniz sesine odaklanma daveti",
      "shells_pool": [
        "Dalgaları dinleyelim.",
        "Bir dondurma alabilir miyim, lütfen?",
        "Hadi kumdan kale yapalım!",
        "Deniz bugün çok güzel."
      ]
    },
    {
      "id": "phr_sum_et_065",
      "mission_phrase": "Can I borrow your snorkel?",
      "target_translation": "Şnorkelini ödünç alabilir miyim?",
      "clue_text": "Suyun altından nefes alan borulu maskeyi isterken",
      "shells_pool": [
        "Şnorkelini ödünç alabilir miyim?",
        "Bir dondurma alabilir miyim, lütfen?",
        "Hadi kumdan kale yapalım!",
        "Deniz bugün çok güzel."
      ]
    },
    {
      "id": "phr_sum_et_066",
      "mission_phrase": "I can swim very fast.",
      "target_translation": "Çok hızlı yüzebilirim.",
      "clue_text": "Suda ne kadar iyi ve süratli ilerlediğini överken",
      "shells_pool": [
        "Çok hızlı yüzebilirim.",
        "Bir dondurma alabilir miyim, lütfen?",
        "Hadi kumdan kale yapalım!",
        "Deniz bugün çok güzel."
      ]
    },
    {
      "id": "phr_sum_et_067",
      "mission_phrase": "Look at the colorful fish!",
      "target_translation": "Renkli balığa bak!",
      "clue_text": "Deniz gözlüğüyle suyun altına bakıp canlıyı görünce",
      "shells_pool": [
        "Renkli balığa bak!",
        "Bir dondurma alabilir miyim, lütfen?",
        "Hadi kumdan kale yapalım!",
        "Deniz bugün çok güzel."
      ]
    },
    {
      "id": "phr_sum_et_068",
      "mission_phrase": "We are packing the car.",
      "target_translation": "Arabayı yerleştiriyoruz.",
      "clue_text": "Yolculuk öncesi valizleri bagaja koyarken",
      "shells_pool": [
        "Arabayı yerleştiriyoruz.",
        "Bir dondurma alabilir miyim, lütfen?",
        "Hadi kumdan kale yapalım!",
        "Deniz bugün çok güzel."
      ]
    },
    {
      "id": "phr_sum_et_069",
      "mission_phrase": "Is there wifi in the room?",
      "target_translation": "Odada internet var mı?",
      "clue_text": "Otel odasında kablosuz ağ bağlantısını sorarken",
      "shells_pool": [
        "Odada internet var mı?",
        "Bir dondurma alabilir miyim, lütfen?",
        "Hadi kumdan kale yapalım!",
        "Deniz bugün çok güzel."
      ]
    },
    {
      "id": "phr_sum_et_070",
      "mission_phrase": "I want to stay here forever.",
      "target_translation": "Sonsuza kadar burada kalmak istiyorum.",
      "clue_text": "Tatil yerini o kadar çok sevip dönmek istemezken",
      "shells_pool": [
        "Sonsuza kadar burada kalmak istiyorum.",
        "Bir dondurma alabilir miyim, lütfen?",
        "Hadi kumdan kale yapalım!",
        "Deniz bugün çok güzel."
      ]
    },
    {
      "id": "phr_sum_et_071",
      "mission_phrase": "Let's run into the sea!",
      "target_translation": "Hadi denize koşalım!",
      "clue_text": "Kumsaldan suya doğru hızlıca koşma daveti",
      "shells_pool": [
        "Hadi denize koşalım!",
        "Bir dondurma alabilir miyim, lütfen?",
        "Hadi kumdan kale yapalım!",
        "Deniz bugün çok güzel."
      ]
    },
    {
      "id": "phr_sum_et_072",
      "mission_phrase": "Can we buy a postcard?",
      "target_translation": "Kartpostal satın alabilir miyiz?",
      "clue_text": "Üzerinde manzara resmi olan tebrik kartı isterken",
      "shells_pool": [
        "Kartpostal satın alabilir miyiz?",
        "Bir dondurma alabilir miyim, lütfen?",
        "Hadi kumdan kale yapalım!",
        "Deniz bugün çok güzel."
      ]
    },
    {
      "id": "phr_sum_et_073",
      "mission_phrase": "The nature is beautiful here.",
      "target_translation": "Burada doğa çok güzel.",
      "clue_text": "Yeşillik, ağaçlar ve çevrenin harikalığını överken",
      "shells_pool": [
        "Burada doğa çok güzel.",
        "Bir dondurma alabilir miyim, lütfen?",
        "Hadi kumdan kale yapalım!",
        "Deniz bugün çok güzel."
      ]
    },
    {
      "id": "phr_sum_et_074",
      "mission_phrase": "I am learning English on vacation.",
      "target_translation": "Tatilde İngilizce öğreniyorum.",
      "clue_text": "Memolandum oynayarak vakit geçirdiğini anlatırken",
      "shells_pool": [
        "Tatilde İngilizce öğreniyorum.",
        "Bir dondurma alabilir miyim, lütfen?",
        "Hadi kumdan kale yapalım!",
        "Deniz bugün çok güzel."
      ]
    },
    {
      "id": "phr_sum_et_075",
      "mission_phrase": "Where is the ice cream shop?",
      "target_translation": "Dondurmacı nerede?",
      "clue_text": "Külah külah tatlı satan dükkanı ararken",
      "shells_pool": [
        "Dondurmacı nerede?",
        "Bir dondurma alabilir miyim, lütfen?",
        "Hadi kumdan kale yapalım!",
        "Deniz bugün çok güzel."
      ]
    },
    {
      "id": "phr_sum_et_076",
      "mission_phrase": "Let's climb that small hill.",
      "target_translation": "Şu küçük tepeye tırmanalım.",
      "clue_text": "Kamp yaparken yüksek manzaraya doğru yürüme daveti",
      "shells_pool": [
        "Şu küçük tepeye tırmanalım.",
        "Bir dondurma alabilir miyim, lütfen?",
        "Hadi kumdan kale yapalım!",
        "Deniz bugün çok güzel."
      ]
    },
    {
      "id": "phr_sum_et_077",
      "mission_phrase": "The lake is very calm.",
      "target_translation": "Göl çok dalgasız ve sakin.",
      "clue_text": "Etrafı kapalı tatlı su kütlesinin kıpırtısız halini överken",
      "shells_pool": [
        "Göl çok dalgasız ve sakin.",
        "Bir dondurma alabilir miyim, lütfen?",
        "Hadi kumdan kale yapalım!",
        "Deniz bugün çok güzel."
      ]
    },
    {
      "id": "phr_sum_et_078",
      "mission_phrase": "I need a life jacket.",
      "target_translation": "Can yeleğine ihtiyacım var.",
      "clue_text": "Tekneye binerken veya yüzmeyi öğrenirken takılan koruyucuyu isterken",
      "shells_pool": [
        "Can yeleğine ihtiyacım var.",
        "Bir dondurma alabilir miyim, lütfen?",
        "Hadi kumdan kale yapalım!",
        "Deniz bugün çok güzel."
      ]
    },
    {
      "id": "phr_sum_et_079",
      "mission_phrase": "We saw a waterfall yesterday.",
      "target_translation": "Dün bir şelale gördük.",
      "clue_text": "Yüksekten akan harika su manzarasını anlatırken",
      "shells_pool": [
        "Dün bir şelale gördük.",
        "Bir dondurma alabilir miyim, lütfen?",
        "Hadi kumdan kale yapalım!",
        "Deniz bugün çok güzel."
      ]
    },
    {
      "id": "phr_sum_et_080",
      "mission_phrase": "Can I sit on the sunbed?",
      "target_translation": "Şezlonga oturabilir miyim?",
      "clue_text": "Plajda uzanılan uzun plastik sandalyeyi isterken",
      "shells_pool": [
        "Şezlonga oturabilir miyim?",
        "Bir dondurma alabilir miyim, lütfen?",
        "Hadi kumdan kale yapalım!",
        "Deniz bugün çok güzel."
      ]
    },
    {
      "id": "phr_sum_et_081",
      "mission_phrase": "My skin is getting brown.",
      "target_translation": "Tenim bronzlaşıyor.",
      "clue_text": "Güneş altında kalınca renginin değiştiğini fark edince",
      "shells_pool": [
        "Tenim bronzlaşıyor.",
        "Bir dondurma alabilir miyim, lütfen?",
        "Hadi kumdan kale yapalım!",
        "Deniz bugün çok güzel."
      ]
    },
    {
      "id": "phr_sum_et_082",
      "mission_phrase": "Let's play hide and seek.",
      "target_translation": "Saklambaç oynayalım.",
      "clue_text": "Tatilde akşam çocuklarla bahçede oyun daveti",
      "shells_pool": [
        "Saklambaç oynayalım.",
        "Bir dondurma alabilir miyim, lütfen?",
        "Hadi kumdan kale yapalım!",
        "Deniz bugün çok güzel."
      ]
    },
    {
      "id": "phr_sum_et_083",
      "mission_phrase": "The hotel has a big garden.",
      "target_translation": "Otelin büyük bir bahçesi var.",
      "clue_text": "Kaldığı yerin çimenlik ve ağaçlık alanını överken",
      "shells_pool": [
        "Otelin büyük bir bahçesi var.",
        "Bir dondurma alabilir miyim, lütfen?",
        "Hadi kumdan kale yapalım!",
        "Deniz bugün çok güzel."
      ]
    },
    {
      "id": "phr_sum_et_084",
      "mission_phrase": "Can we order a pizza?",
      "target_translation": "Pizza sipariş edebilir miyiz?",
      "clue_text": "Denizden çıkınca çok acıkıp hamurlu yiyecek isterken",
      "shells_pool": [
        "Pizza sipariş edebilir miyiz?",
        "Bir dondurma alabilir miyim, lütfen?",
        "Hadi kumdan kale yapalım!",
        "Deniz bugün çok güzel."
      ]
    },
    {
      "id": "phr_sum_et_085",
      "mission_phrase": "I love summer fashion.",
      "target_translation": "Yaz modasını seviyorum.",
      "clue_text": "Şort, tişört ve renkli gözlük giyme tarzını överken",
      "shells_pool": [
        "Yaz modasını seviyorum.",
        "Bir dondurma alabilir miyim, lütfen?",
        "Hadi kumdan kale yapalım!",
        "Deniz bugün çok güzel."
      ]
    },
    {
      "id": "phr_sum_et_086",
      "mission_phrase": "Where can I wash my feet?",
      "target_translation": "Ayaklarımı nerede yıkayabilirim?",
      "clue_text": "Plajdan çıkarken kumları temizlemek için musluk ararken",
      "shells_pool": [
        "Ayaklarımı nerede yıkayabilirim?",
        "Bir dondurma alabilir miyim, lütfen?",
        "Hadi kumdan kale yapalım!",
        "Deniz bugün çok güzel."
      ]
    },
    {
      "id": "phr_sum_et_087",
      "mission_phrase": "The sky is completely blue.",
      "target_translation": "Gökyüzü tamamen mavi.",
      "clue_text": "Hiç bulut olmadığını, havanın harika olduğunu söylerken",
      "shells_pool": [
        "Gökyüzü tamamen mavi.",
        "Bir dondurma alabilir miyim, lütfen?",
        "Hadi kumdan kale yapalım!",
        "Deniz bugün çok güzel."
      ]
    },
    {
      "id": "phr_sum_et_088",
      "mission_phrase": "Let's watch a movie tonight.",
      "target_translation": "Bu gece bir film izleyelim.",
      "clue_text": "Tatilde akşam evde veya otelde sinema keyfi teklifi",
      "shells_pool": [
        "Bu gece bir film izleyelim.",
        "Bir dondurma alabilir miyim, lütfen?",
        "Hadi kumdan kale yapalım!",
        "Deniz bugün çok güzel."
      ]
    },
    {
      "id": "phr_sum_et_089",
      "mission_phrase": "I will miss this place.",
      "target_translation": "Burayı özleyeceğim.",
      "clue_text": "Tatil bitip eve dönerken hissedilen burukluk cümlesi",
      "shells_pool": [
        "Burayı özleyeceğim.",
        "Bir dondurma alabilir miyim, lütfen?",
        "Hadi kumdan kale yapalım!",
        "Deniz bugün çok güzel."
      ]
    },
    {
      "id": "phr_sum_et_090",
      "mission_phrase": "Can we go to the zoo?",
      "target_translation": "Hayvanat bahçesine gidebilir miyiz?",
      "clue_text": "Tatilde farklı hayvanları görmek için gezi isterken",
      "shells_pool": [
        "Hayvanat bahçesine gidebilir miyiz?",
        "Bir dondurma alabilir miyim, lütfen?",
        "Hadi kumdan kale yapalım!",
        "Deniz bugün çok güzel."
      ]
    },
    {
      "id": "phr_sum_et_091",
      "mission_phrase": "I am drinking cold tea.",
      "target_translation": "Soğuk çay içiyorum.",
      "clue_text": "Yazın buzlu meyveli çay tüketirken",
      "shells_pool": [
        "Soğuk çay içiyorum.",
        "Bir dondurma alabilir miyim, lütfen?",
        "Hadi kumdan kale yapalım!",
        "Deniz bugün çok güzel."
      ]
    },
    {
      "id": "phr_sum_et_092",
      "mission_phrase": "The airport is huge.",
      "target_translation": "Havalimanı devasa büyük.",
      "clue_text": "Uçağa binmeden önce terminalin büyüklüğünü görünce",
      "shells_pool": [
        "Havalimanı devasa büyük.",
        "Bir dondurma alabilir miyim, lütfen?",
        "Hadi kumdan kale yapalım!",
        "Deniz bugün çok güzel."
      ]
    },
    {
      "id": "phr_sum_et_093",
      "mission_phrase": "Let's wake up for sunrise.",
      "target_translation": "Güneşin doğuşu için uyanalım.",
      "clue_text": "Sabah güneşin ilk çıkış anını yakalamak için plan yaparken",
      "shells_pool": [
        "Güneşin doğuşu için uyanalım.",
        "Bir dondurma alabilir miyim, lütfen?",
        "Hadi kumdan kale yapalım!",
        "Deniz bugün çok güzel."
      ]
    },
    {
      "id": "phr_sum_et_094",
      "mission_phrase": "My suitcase is very heavy.",
      "target_translation": "Valizim çok ağır.",
      "clue_text": "İçine çok fazla kıyafet ve oyuncak koyduğu bavulu taşırken",
      "shells_pool": [
        "Valizim çok ağır.",
        "Bir dondurma alabilir miyim, lütfen?",
        "Hadi kumdan kale yapalım!",
        "Deniz bugün çok güzel."
      ]
    },
    {
      "id": "phr_sum_et_095",
      "mission_phrase": "Can I have a cold drink?",
      "target_translation": "Soğuk bir içecek alabilir miyim?",
      "clue_text": "Sıcak havada dolaptan buz gibi sıvı isterken",
      "shells_pool": [
        "Soğuk bir içecek alabilir miyim?",
        "Bir dondurma alabilir miyim, lütfen?",
        "Hadi kumdan kale yapalım!",
        "Deniz bugün çok güzel."
      ]
    },
    {
      "id": "phr_sum_et_096",
      "mission_phrase": "We are going back home on Sunday.",
      "target_translation": "Pazar günü eve geri dönüyoruz.",
      "clue_text": "Tatilin bitiş gününü aile içinde konuşurken",
      "shells_pool": [
        "Pazar günü eve geri dönüyoruz.",
        "Bir dondurma alabilir miyim, lütfen?",
        "Hadi kumdan kale yapalım!",
        "Deniz bugün çok güzel."
      ]
    },
    {
      "id": "phr_sum_et_097",
      "mission_phrase": "This is the best summer ever.",
      "target_translation": "Bu şimdiye kadarki en iyi yaz.",
      "clue_text": "Hayatındaki en eğlenceli tatili geçirdiğini söylerken",
      "shells_pool": [
        "Bu şimdiye kadarki en iyi yaz.",
        "Bir dondurma alabilir miyim, lütfen?",
        "Hadi kumdan kale yapalım!",
        "Deniz bugün çok güzel."
      ]
    },
    {
      "id": "phr_sum_et_098",
      "mission_phrase": "I am learning how to surf.",
      "target_translation": "Sörf yapmayı öğreniyorum.",
      "clue_text": "Dalgaların üzerinde tahtayla kayma eğitimi alırken",
      "shells_pool": [
        "Sörf yapmayı öğreniyorum.",
        "Bir dondurma alabilir miyim, lütfen?",
        "Hadi kumdan kale yapalım!",
        "Deniz bugün çok güzel."
      ]
    },
    {
      "id": "phr_sum_et_099",
      "mission_phrase": "Can you pass me the ball?",
      "target_translation": "Topu bana pas atabilir miyiz?",
      "clue_text": "Oyunda arkadaşından yuvarlak nesneyi fırlatmasını isterken",
      "shells_pool": [
        "Topu bana pas atabilir miyiz?",
        "Bir dondurma alabilir miyim, lütfen?",
        "Hadi kumdan kale yapalım!",
        "Deniz bugün çok güzel."
      ]
    },
    {
      "id": "phr_sum_et_100",
      "mission_phrase": "Have a great summer vacation!",
      "target_translation": "Harika bir yaz tatili geçirin!",
      "clue_text": "Okulun son günü arkadaşlara veda ederken söylenen dilek",
      "shells_pool": [
        "Harika bir yaz tatili geçirin!",
        "Bir dondurma alabilir miyim, lütfen?",
        "Hadi kumdan kale yapalım!",
        "Deniz bugün çok güzel."
      ]
    }
  ]
}