[
  { "id": 101, "osmanlica_latin": "Fıtrat", "osmanlica_arapca": "فطرت", "guncel_turkce": "Yaratılış, doğal yapı, karakter" },
  { "id": 102, "osmanlica_latin": "Gafil", "osmanlica_arapca": "غافل", "guncel_turkce": "Habersiz, aymaz, dikkatsiz" },
  { "id": 103, "osmanlica_latin": "Garezkâr", "osmanlica_arapca": "غرضكار", "guncel_turkce": "Kin besleyen, garazı olan" },
  { "id": 104, "osmanlica_latin": "Gayret", "osmanlica_arapca": "غيرت", "guncel_turkce": "Çaba, çalışma isteği" },
  { "id": 105, "osmanlica_latin": "Gaye", "osmanlica_arapca": "غايه", "guncel_turkce": "Amaç, hedef, ülkü" },
  { "id": 106, "osmanlica_latin": "Gıyap", "osmanlica_arapca": "غياب", "guncel_turkce": "Bulunmama durumu, arkasından" },
  { "id": 107, "osmanlica_latin": "Gurbet", "osmanlica_arapca": "غربt", "guncel_turkce": "Yabancı yer, sıla özlemi" },
  { "id": 108, "osmanlica_latin": "Gülzar", "osmanlica_arapca": "گلزار", "guncel_turkce": "Gül bahçesi" },
  { "id": 109, "osmanlica_latin": "Güzide", "osmanlica_arapca": "گزيده", "guncel_turkce": "Seçkin, seçilmiş, beğenilmiş" },
  { "id": 110, "osmanlica_latin": "Habis", "osmanlica_arapca": "خبيث", "guncel_turkce": "Kötü, alçak, uğursuz" },
  { "id": 111, "osmanlica_latin": "Hacet", "osmanlica_arapca": "حاجت", "guncel_turkce": "İhtiyaç, gerekli olan şey" },
  { "id": 112, "osmanlica_latin": "Hafıza", "osmanlica_arapca": "حافظه", "guncel_turkce": "Bellek, dağarcık" },
  { "id": 113, "osmanlica_latin": "Hakan", "osmanlica_arapca": "خاقان", "guncel_turkce": "Büyük hükümdar, kağan" },
  { "id": 114, "osmanlica_latin": "Hakikat", "osmanlica_arapca": "حقيقت", "guncel_turkce": "Gerçek, asıl, doğru" },
  { "id": 115, "osmanlica_latin": "Hakim", "osmanlica_arapca": "حاكم", "guncel_turkce": "Yargıç, egemen olan" },
  { "id": 116, "osmanlica_latin": "Halis", "osmanlica_arapca": "خالص", "guncel_turkce": "Katışıksız, saf, temiz" },
  { "id": 117, "osmanlica_latin": "Haluk", "osmanlica_arapca": "خلوق", "guncel_turkce": "İyi ahlaklı, temiz huylu" },
  { "id": 118, "osmanlica_latin": "Hamiyet", "osmanlica_arapca": "حميت", "guncel_turkce": "Milli onur ve haysiyet duygusu" },
  { "id": 119, "osmanlica_latin": "Hararet", "osmanlica_arapca": "حرارت", "guncel_turkce": "Sıcaklık, susuzluk, coşku" },
  { "id": 120, "osmanlica_latin": "Harap", "osmanlica_arapca": "خراب", "guncel_turkce": "Yıkık, bozuk, perişan" },
  { "id": 121, "osmanlica_latin": "Hasret", "osmanlica_arapca": "حسرت", "guncel_turkce": "Özlem, kavuşma isteği" },
  { "id": 122, "osmanlica_latin": "Hassasiyet", "osmanlica_arapca": "حساسيت", "guncel_turkce": "Duyarlılık, incelik" },
  { "id": 123, "osmanlica_latin": "Hata", "osmanlica_arapca": "خطا", "guncel_turkce": "Yanlışlık, kusur, günah" },
  { "id": 124, "osmanlica_latin": "Hayal", "osmanlica_arapca": "خيال", "guncel_turkce": "Zihindeki canlandırma, imge" },
  { "id": 125, "osmanlica_latin": "Hayat", "osmanlica_arapca": "حيات", "guncel_turkce": "Yaşam, canlılık" },
  { "id": 126, "osmanlica_latin": "Haysiyet", "osmanlica_arapca": "حيثيت", "guncel_turkce": "Onur, şeref, saygınlık" },
  { "id": 127, "osmanlica_latin": "Hazin", "osmanlica_arapca": "حزين", "guncel_turkce": "Hüzünlü, acıklı, üzüntülü" },
  { "id": 128, "osmanlica_latin": "Hazine", "osmanlica_arapca": "خزينه", "guncel_turkce": "Gömü, değerli şeylerin saklandığı yer" },
  { "id": 129, "osmanlica_latin": "Hediyye", "osmanlica_arapca": "هديه", "guncel_turkce": "Armağan, ödül" },
  { "id": 130, "osmanlica_latin": "Hemşire", "osmanlica_arapca": "همشيره", "guncel_turkce": "Kız kardeş, sağlık görevlisi" },
  { "id": 131, "osmanlica_latin": "Heves", "osmanlica_arapca": "هوس", "guncel_turkce": "Geçici istek, eğilim" },
  { "id": 132, "osmanlica_latin": "Hidayet", "osmanlica_arapca": "هدايت", "guncel_turkce": "Doğru yola erme, hak yolu" },
  { "id": 133, "osmanlica_latin": "Hikmet", "osmanlica_arapca": "حكمت", "guncel_turkce": "Derin neden, gizli bilgelik" },
  { "id": 134, "osmanlica_latin": "Hilal", "osmanlica_arapca": "هلال", "guncel_turkce": "Yeni ay, ayça" },
  { "id": 135, "osmanlica_latin": "Hususi", "osmanlica_arapca": "خصوصى", "guncel_turkce": "Özel, kişisel" },
  { "id": 136, "osmanlica_latin": "Huzur", "osmanlica_arapca": "حضور", "guncel_turkce": "Gönül rahatlığı, dirlik, makam" },
  { "id": 137, "osmanlica_latin": "Hüsnüniyet", "osmanlica_arapca": "حسن نيت", "guncel_turkce": "İyi niyet, temiz yüreklilik" },
  { "id": 138, "osmanlica_latin": "Hüzün", "osmanlica_arapca": "حزن", "guncel_turkce": "Gönül üzüntüsü, keder" },
  { "id": 139, "osmanlica_latin": "İbadet", "osmanlica_arapca": "عبادت", "guncel_turkce": "Tapınma, kulluk görevleri" },
  { "id": 140, "osmanlica_latin": "İbare", "osmanlica_arapca": "باره", "guncel_turkce": "Söz dizisi, cümle, ifade" },
  { "id": 141, "osmanlica_latin": "İbret", "osmanlica_arapca": "عبرت", "guncel_turkce": "Ders alınacak durum, uyarı" },
  { "id": 142, "osmanlica_latin": "İçtihat", "osmanlica_arapca": "اجتهاد", "guncel_turkce": "Yasa hükmü çıkarma, görüş" },
  { "id": 143, "osmanlica_latin": "İrade", "osmanlica_arapca": "اراده", "guncel_turkce": "İsteme gücü, seçim yapabilme yetisi" },
  { "id": 144, "osmanlica_latin": "İrfan", "osmanlica_arapca": "عرفan", "guncel_turkce": "Bilme, anlama, kültürel birikim" },
  { "id": 145, "osmanlica_latin": "İstikbal", "osmanlica_arapca": "استقبال", "guncel_turkce": "Gelecek zaman, karşılama" },
  { "id": 146, "osmanlica_latin": "İstiklal", "osmanlica_arapca": "استقلال", "guncel_turkce": "Bağımsızlık, özgürlük" },
  { "id": 147, "osmanlica_latin": "İtimat", "osmanlica_arapca": "اعتماد", "guncel_turkce": "Güvenme, inanma" },
  { "id": 148, "osmanlica_latin": "Kabiliyet", "osmanlica_arapca": "قابليت", "guncel_turkce": "Yetenek, güç, elverişlilik" },
  { "id": 149, "osmanlica_latin": "Kader", "osmanlica_arapca": "قدر", "guncel_turkce": "Yazgı, alın yazısı, ölçü" },
  { "id": 150, "osmanlica_latin": "Kalp", "osmanlica_arapca": "قلب", "guncel_turkce": "Yürek, gönül, merkez" },
  { "id": 151, "osmanlica_latin": "Kamer", "osmanlica_arapca": "قمر", "guncel_turkce": "Ay, gök cismi" },
  { "id": 152, "osmanlica_latin": "Kanaat", "osmanlica_arapca": "قناعت", "guncel_turkce": "Yetenme, elindekini yeterli bulma" },
  { "id": 153, "osmanlica_latin": "Kanun", "osmanlica_arapca": "قانون", "guncel_turkce": "Yasa, kural, düzen" },
  { "id": 154, "osmanlica_latin": "Kelim", "osmanlica_arapca": "كليم", "guncel_turkce": "Konuşan, söz söyleyen" },
  { "id": 155, "osmanlica_latin": "Kerem", "osmanlica_arapca": "كرم", "guncel_turkce": "Soylu cömertlik, lütuf" },
  { "id": 156, "osmanlica_latin": "Keşif", "osmanlica_arapca": "كشف", "guncel_turkce": "Gizli olanı açığa çıkarma, bulma" },
  { "id": 157, "osmanlica_latin": "Kifayet", "osmanlica_arapca": "كفايت", "guncel_turkce": "Yeterlilik, yetişme" },
  { "id": 158, "osmanlica_latin": "Kitab", "osmanlica_arapca": "كتاب", "guncel_turkce": "Yazılmış eser, kitap" },
  { "id": 159, "osmanlica_latin": "Kudret", "osmanlica_arapca": "قدرت", "guncel_turkce": "Güç, kuvvet, yetenek" },
  { "id": 160, "osmanlica_latin": "Lafız", "osmanlica_arapca": "لفظ", "guncel_turkce": "Söz, kelime, dış ses" },
  { "id": 161, "osmanlica_latin": "Latif", "osmanlica_arapca": "لطيف", "guncel_turkce": "Yumuşak, hoş, nazik" },
  { "id": 162, "osmanlica_latin": "Liyakat", "osmanlica_arapca": "لياقت", "guncel_turkce": "Yaraşırlık, uygunluk, yetenek" },
  { "id": 163, "osmanlica_latin": "Lütuf", "osmanlica_arapca": "لطف", "guncel_turkce": "Hoşluk, iyilik, ikram" },
  { "id": 164, "osmanlica_latin": "Maarif", "osmanlica_arapca": "معارف", "guncel_turkce": "Eğitim ve öğretim sistemi, kültür" },
  { "id": 165, "osmanlica_latin": "Makam", "osmanlica_arapca": "مقام", "guncel_turkce": "Mevki, rütbe, durak" },
  { "id": 166, "osmanlica_latin": "Malum", "osmanlica_arapca": "معلوم", "guncel_turkce": "Bilinen, belli olan" },
  { "id": 167, "osmanlica_latin": "Manidar", "osmanlica_arapca": "معنى دار", "guncel_turkce": "Anlamlı, düşündürücü" },
  { "id": 168, "osmanlica_latin": "Marifet", "osmanlica_arapca": "معرفت", "guncel_turkce": "Ustalık, hüner, bilme" },
  { "id": 169, "osmanlica_latin": "Matbuat", "osmanlica_arapca": "مطبوعات", "guncel_turkce": "Basın, basılı eserler" },
  { "id": 170, "osmanlica_latin": "Mecbur", "osmanlica_arapca": "مجبور", "guncel_turkce": "Zorunlu, yükümlü" },
  { "id": 171, "osmanlica_latin": "Medeniyet", "osmanlica_arapca": "مدنيت", "guncel_turkce": "Uygarlık" },
  { "id": 172, "osmanlica_latin": "Meftun", "osmanlica_arapca": "مفتون", "guncel_turkce": "Hayran olmuş, tutkun, gönül vermiş" },
  { "id": 173, "osmanlica_latin": "Melal", "osmanlica_arapca": "ملال", "guncel_turkce": "Hüzün, can sıkıntısı, iç ezikliği" },
  { "id": 174, "osmanlica_latin": "Memleket", "osmanlica_arapca": "مملكت", "guncel_turkce": "Ülke, yurt, memleket" },
  { "id": 175, "osmanlica_latin": "Menzil", "osmanlica_arapca": "منزل", "guncel_turkce": "Varılacak yer, hedef, konak" },
  { "id": 176, "osmanlica_latin": "Merhamet", "osmanlica_arapca": "مرحمت", "guncel_turkce": "Acıma, şefkat gösterme" },
  { "id": 177, "osmanlica_latin": "Mesafe", "osmanlica_arapca": "مسافه", "guncel_turkce": "Ara, uzaklık" },
  { "id": 178, "osmanlica_latin": "Mesut", "osmanlica_arapca": "مسعود", "guncel_turkce": "Mutlu, kutlu, sevinçli" },
  { "id": 179, "osmanlica_latin": "Meşru", "osmanlica_arapca": "مشروع", "guncel_turkce": "Yasalara uygun, geçerli" },
  { "id": 180, "osmanlica_latin": "Mevsim", "osmanlica_arapca": "موسم", "guncel_turkce": "Dönem, çağ, yılın dört bölümü" },
  { "id": 181, "osmanlica_latin": "Meydan", "osmanlica_arapca": "ميدان", "guncel_turkce": "Açık alan, alan" },
  { "id": 182, "osmanlica_latin": "Miras", "osmanlica_arapca": "ميراث", "guncel_turkce": "Ölenlerden kalan mal veya kültür" },
  { "id": 183, "osmanlica_latin": "Mizan", "osmanlica_arapca": "ميزان", "guncel_turkce": "Terazi, ölçü, denge" },
  { "id": 184, "osmanlica_latin": "Muazzam", "osmanlica_arapca": "معظم", "guncel_turkce": "Çok büyük, görkemli" },
  { "id": 185, "osmanlica_latin": "Muhabbet", "osmanlica_arapca": "محبت", "guncel_turkce": "Sevgi, dostça konuşma" },
  { "id": 186, "osmanlica_latin": "Mukaddes", "osmanlica_arapca": "مقدس", "guncel_turkce": "Kutsal, kutsanmış" },
  { "id": 187, "osmanlica_latin": "Mutluluk", "osmanlica_arapca": "سعادت", "guncel_turkce": "Saadet, ongunluk" },
  { "id": 188, "osmanlica_latin": "Mücella", "osmanlica_arapca": "مجلى", "guncel_turkce": "Parlatılmış, parlak" },
  { "id": 189, "osmanlica_latin": "Mürekkep", "osmanlica_arapca": "مركب", "guncel_turkce": "Birleşmiş, yazı sıvısı" },
  { "id": 190, "osmanlica_latin": "Müşfik", "osmanlica_arapca": "مشفق", "guncel_turkce": "Şefkatli, sevecen" },
  { "id": 191, "osmanlica_latin": "Nadir", "osmanlica_arapca": "نادر", "guncel_turkce": "Ender, az bulunan" },
  { "id": 192, "osmanlica_latin": "Nasihat", "osmanlica_arapca": "نصيحت", "guncel_turkce": "Öğüt, tavsiye" },
  { "id": 193, "osmanlica_latin": "Nazik", "osmanlica_arapca": "نازك", "guncel_turkce": "İnce, kibar, narin" },
  { "id": 194, "osmanlica_latin": "Nefes", "osmanlica_arapca": "نفس", "guncel_turkce": "Soluk, canlılık emaresi" },
  { "id": 195, "osmanlica_latin": "Nimet", "osmanlica_arapca": "نعمت", "guncel_turkce": "İyilik, lütuf, rızık" },
  { "id": 196, "osmanlica_latin": "Niyet", "osmanlica_arapca": "نيت", "guncel_turkce": "Maksat, tasarı, kalpteki amaç" },
  { "id": 197, "osmanlica_latin": "Nur", "osmanlica_arapca": "نور", "guncel_turkce": "Aydınlık, parıltı, kutsal ışık" },
  { "id": 198, "osmanlica_latin": "Rüya", "osmanlica_arapca": "رؤيا", "guncel_turkce": "Düş, uykudaki imge" },
  { "id": 199, "osmanlica_latin": "Sabır", "osmanlica_arapca": "صبر", "guncel_turkce": "Katlanma, dayanma gücü" },
  { "id": 200, "osmanlica_latin": "Zaman", "osmanlica_arapca": "زمان", "guncel_turkce": "Vakit, dönem, süre" }
]