[
  {
    "id": 1,
    "word": "abruptly",
    "translation": "aniden, birdenbire, pat diye",
    "pos": "adverb",
    "tags": [
      "YDS"
    ],
    "audioUrl": "/data/data/Tr_Eng_YDS_kelimeleri/audio_yds/abruptly.mp3"
  },
  {
    "id": 2,
    "word": "abstain",
    "translation": "kaçınmak, uzak durmak, oy vermemek/çekimser kalmak (-from ile kullanılır)",
    "pos": "verb",
    "tags": [
      "YDS"
    ],
    "audioUrl": "/data/data/Tr_Eng_YDS_kelimeleri/audio_yds/abstain.mp3"
  },
  {
    "id": 3,
    "word": "acclaim",
    "translation": "övgüyle karşılamak, alkışlamak / övgü, beğeni",
    "pos": "verb/noun",
    "tags": [
      "YDS"
    ],
    "audioUrl": "/data/data/Tr_Eng_YDS_kelimeleri/audio_yds/acclaim.mp3"
  },
  {
    "id": 4,
    "word": "accomplice",
    "translation": "suç ortağı",
    "pos": "noun",
    "tags": [
      "YDS"
    ],
    "audioUrl": "/data/data/Tr_Eng_YDS_kelimeleri/audio_yds/accomplice.mp3"
  },
  {
    "id": 5,
    "word": "adhere",
    "translation": "(kurala/inanca) sadık kalmak, bağlı olmak, yapışmak (-to ile kullanılır)",
    "pos": "verb",
    "tags": [
      "YDS"
    ],
    "audioUrl": "/data/data/Tr_Eng_YDS_kelimeleri/audio_yds/adhere.mp3"
  },
  {
    "id": 6,
    "word": "adversary",
    "translation": "rakip, düşman, karşı taraf",
    "pos": "noun",
    "tags": [
      "YDS"
    ],
    "audioUrl": "/data/data/Tr_Eng_YDS_kelimeleri/audio_yds/adversary.mp3"
  },
  {
    "id": 7,
    "word": "affluent",
    "translation": "zengin, varlıklı, refah içinde",
    "pos": "adjective",
    "tags": [
      "YDS"
    ],
    "audioUrl": "/data/data/Tr_Eng_YDS_kelimeleri/audio_yds/affluent.mp3"
  },
  {
    "id": 8,
    "word": "aggravate",
    "translation": "kötüleştirmek, şiddetlendirmek, çileden çıkarmak",
    "pos": "verb",
    "tags": [
      "YDS"
    ],
    "audioUrl": "/data/data/Tr_Eng_YDS_kelimeleri/audio_yds/aggravate.mp3"
  },
  {
    "id": 9,
    "word": "alleviate",
    "translation": "(acı, hafifletmek, dindirmek, azaltmak)",
    "pos": "verb",
    "tags": [
      "YDS"
    ],
    "audioUrl": "/data/data/Tr_Eng_YDS_kelimeleri/audio_yds/alleviate.mp3"
  },
  {
    "id": 10,
    "word": "ambiguity",
    "translation": "belirsizlik, muğlaklık, çift anlamlılık",
    "pos": "noun",
    "tags": [
      "YDS"
    ],
    "audioUrl": "/data/data/Tr_Eng_YDS_kelimeleri/audio_yds/ambiguity.mp3"
  },
  {
    "id": 11,
    "word": "annihilate",
    "translation": "yok etmek, kökünü kazımak, tamamen yok etmek",
    "pos": "verb",
    "tags": [
      "YDS"
    ],
    "audioUrl": "/data/data/Tr_Eng_YDS_kelimeleri/audio_yds/annihilate.mp3"
  },
  {
    "id": 12,
    "word": "anonymous",
    "translation": "isimsiz, anonim, gizli",
    "pos": "adjective",
    "tags": [
      "YDS"
    ],
    "audioUrl": "/data/data/Tr_Eng_YDS_kelimeleri/audio_yds/anonymous.mp3"
  },
  {
    "id": 13,
    "word": "apprehend",
    "translation": "yakalamak/tutuklamak, endişeyle kavramak/anlamak",
    "pos": "verb",
    "tags": [
      "YDS"
    ],
    "audioUrl": "/data/data/Tr_Eng_YDS_kelimeleri/audio_yds/apprehend.mp3"
  },
  {
    "id": 14,
    "word": "articulate",
    "translation": "açıkça ifade etmek, dile getirmek / akıcı, net ifade edilen",
    "pos": "verb/adjective",
    "tags": [
      "YDS"
    ],
    "audioUrl": "/data/data/Tr_Eng_YDS_kelimeleri/audio_yds/articulate.mp3"
  },
  {
    "id": 15,
    "word": "ascribe",
    "translation": "-e dayandırmak, -e atfetmek (-to ile kullanılır)",
    "pos": "verb",
    "tags": [
      "YDS"
    ],
    "audioUrl": "/data/data/Tr_Eng_YDS_kelimeleri/audio_yds/ascribe.mp3"
  },
  {
    "id": 16,
    "word": "assiduous",
    "translation": "çalışkan, gayretli, özenli",
    "pos": "adjective",
    "tags": [
      "YDS"
    ],
    "audioUrl": "/data/data/Tr_Eng_YDS_kelimeleri/audio_yds/assiduous.mp3"
  },
  {
    "id": 17,
    "word": "astute",
    "translation": "kurnaz, zeki, işini bilen, gözü açık",
    "pos": "adjective",
    "tags": [
      "YDS"
    ],
    "audioUrl": "/data/data/Tr_Eng_YDS_kelimeleri/audio_yds/astute.mp3"
  },
  {
    "id": 18,
    "word": "atrocity",
    "translation": "gaddarlık, vahşet, zulüm",
    "pos": "noun",
    "tags": [
      "YDS"
    ],
    "audioUrl": "/data/data/Tr_Eng_YDS_kelimeleri/audio_yds/atrocity.mp3"
  },
  {
    "id": 19,
    "word": "audacious",
    "translation": "cesur, cüretkar, küstahça cesur",
    "pos": "adjective",
    "tags": [
      "YDS"
    ],
    "audioUrl": "/data/data/Tr_Eng_YDS_kelimeleri/audio_yds/audacious.mp3"
  },
  {
    "id": 20,
    "word": "avert",
    "translation": "(kötü bir şeyi) önlemek, başka yöne çevirmek (göz vb.)",
    "pos": "verb",
    "tags": [
      "YDS"
    ],
    "audioUrl": "/data/data/Tr_Eng_YDS_kelimeleri/audio_yds/avert.mp3"
  },
  {
    "id": 21,
    "word": "baffle",
    "translation": "şaşırtmak, aklını karıştırmak, hüsrana uğratmak",
    "pos": "verb",
    "tags": [
      "YDS"
    ],
    "audioUrl": "/data/data/Tr_Eng_YDS_kelimeleri/audio_yds/baffle.mp3"
  },
  {
    "id": 22,
    "word": "belligerent",
    "translation": "savaşçı, saldırgan, kavgacı",
    "pos": "adjective",
    "tags": [
      "YDS"
    ],
    "audioUrl": "/data/data/Tr_Eng_YDS_kelimeleri/audio_yds/belligerent.mp3"
  },
  {
    "id": 23,
    "word": "benevolent",
    "translation": "hayırsever, iyiliksever, sevecen",
    "pos": "adjective",
    "tags": [
      "YDS"
    ],
    "audioUrl": "/data/data/Tr_Eng_YDS_kelimeleri/audio_yds/benevolent.mp3"
  },
  {
    "id": 24,
    "word": "blatant",
    "translation": "apaçık, bariz, küstahça ortada olan",
    "pos": "adjective",
    "tags": [
      "YDS"
    ],
    "audioUrl": "/data/data/Tr_Eng_YDS_kelimeleri/audio_yds/blatant.mp3"
  },
  {
    "id": 25,
    "word": "bolster",
    "translation": "güçlendirmek, desteklemek, moral vermek",
    "pos": "verb",
    "tags": [
      "YDS"
    ],
    "audioUrl": "/data/data/Tr_Eng_YDS_kelimeleri/audio_yds/bolster.mp3"
  },
  {
    "id": 26,
    "word": "boycott",
    "translation": "boykot etmek / boykot",
    "pos": "verb/noun",
    "tags": [
      "YDS"
    ],
    "audioUrl": "/data/data/Tr_Eng_YDS_kelimeleri/audio_yds/boycott.mp3"
  },
  {
    "id": 27,
    "word": "breach",
    "translation": "ihlal, gedik, yarık / ihlal etmek",
    "pos": "noun/verb",
    "tags": [
      "YDS"
    ],
    "audioUrl": "/data/data/Tr_Eng_YDS_kelimeleri/audio_yds/breach.mp3"
  },
  {
    "id": 28,
    "word": "candid",
    "translation": "samimi, içten, açık sözlü, dobrasözlü",
    "pos": "adjective",
    "tags": [
      "YDS"
    ],
    "audioUrl": "/data/data/Tr_Eng_YDS_kelimeleri/audio_yds/candid.mp3"
  },
  {
    "id": 29,
    "word": "capricious",
    "translation": "kaprisli, değişken, maymun iştahlı, fevri",
    "pos": "adjective",
    "tags": [
      "YDS"
    ],
    "audioUrl": "/data/data/Tr_Eng_YDS_kelimeleri/audio_yds/capricious.mp3"
  },
  {
    "id": 30,
    "word": "chronicle",
    "translation": "tarih sırasına göre kaydetmek / vekayiname, kronik tarih",
    "pos": "verb/noun",
    "tags": [
      "YDS"
    ],
    "audioUrl": "/data/data/Tr_Eng_YDS_kelimeleri/audio_yds/chronicle.mp3"
  },
  {
    "id": 31,
    "word": "coercion",
    "translation": "baskı, zorlama, icbar",
    "pos": "noun",
    "tags": [
      "YDS"
    ],
    "audioUrl": "/data/data/Tr_Eng_YDS_kelimeleri/audio_yds/coercion.mp3"
  },
  {
    "id": 32,
    "word": "cognitive",
    "translation": "bilişsel, kavramsal, zihinsel",
    "pos": "adjective",
    "tags": [
      "YDS"
    ],
    "audioUrl": "/data/data/Tr_Eng_YDS_kelimeleri/audio_yds/cognitive.mp3"
  },
  {
    "id": 33,
    "word": "coherent",
    "translation": "tutarlı, anlaşılır, mantıklı bir şekilde birleşen",
    "pos": "adjective",
    "tags": [
      "YDS"
    ],
    "audioUrl": "/data/data/Tr_Eng_YDS_kelimeleri/audio_yds/coherent.mp3"
  },
  {
    "id": 34,
    "word": "coincide",
    "translation": "aynı zamana denk gelmek, uyuşmak (-with ile kullanılır)",
    "pos": "verb",
    "tags": [
      "YDS"
    ],
    "audioUrl": "/data/data/Tr_Eng_YDS_kelimeleri/audio_yds/coincide.mp3"
  },
  {
    "id": 35,
    "word": "collaborate",
    "translation": "iş birliği yapmak (ortak proje, bilim vb.)",
    "pos": "verb",
    "tags": [
      "YDS"
    ],
    "audioUrl": "/data/data/Tr_Eng_YDS_kelimeleri/audio_yds/collaborate.mp3"
  },
  {
    "id": 36,
    "word": "commend",
    "translation": "övgüyle söz etmek, tavsiye etmek, emanet etmek",
    "pos": "verb",
    "tags": [
      "YDS"
    ],
    "audioUrl": "/data/data/Tr_Eng_YDS_kelimeleri/audio_yds/commend.mp3"
  },
  {
    "id": 37,
    "word": "commodity",
    "translation": "ticari mal, eşya, hammadde",
    "pos": "noun",
    "tags": [
      "YDS"
    ],
    "audioUrl": "/data/data/Tr_Eng_YDS_kelimeleri/audio_yds/commodity.mp3"
  },
  {
    "id": 38,
    "word": "compatible",
    "translation": "uyumlu, geçimli (-with ile kullanılır)",
    "pos": "adjective",
    "tags": [
      "YDS"
    ],
    "audioUrl": "/data/data/Tr_Eng_YDS_kelimeleri/audio_yds/compatible.mp3"
  },
  {
    "id": 39,
    "word": "compelling",
    "translation": "ikna edici, zorunlu kılan, çok ilgi çekici",
    "pos": "adjective",
    "tags": [
      "YDS"
    ],
    "audioUrl": "/data/data/Tr_Eng_YDS_kelimeleri/audio_yds/compelling.mp3"
  },
  {
    "id": 40,
    "word": "complacent",
    "translation": "hâline razı, kendinden memnun (tehlikeli rahatlık)",
    "pos": "adjective",
    "tags": [
      "YDS"
    ],
    "audioUrl": "/data/data/Tr_Eng_YDS_kelimeleri/audio_yds/complacent.mp3"
  },
  {
    "id": 41,
    "word": "comply",
    "translation": "(kurala, kanuna vb.) uymak, boyun eğmek (-with ile kullanılır)",
    "pos": "verb",
    "tags": [
      "YDS"
    ],
    "audioUrl": "/data/data/Tr_Eng_YDS_kelimeleri/audio_yds/comply.mp3"
  },
  {
    "id": 42,
    "word": "compromise",
    "translation": "uzlaşmak, ödün vermek / uzlaşma, orta yol",
    "pos": "verb/noun",
    "tags": [
      "YDS"
    ],
    "audioUrl": "/data/data/Tr_Eng_YDS_kelimeleri/audio_yds/compromise.mp3"
  },
  {
    "id": 43,
    "word": "compulsory",
    "translation": "zorunlu, mecburi, yasal dayatması olan",
    "pos": "adjective",
    "tags": [
      "YDS"
    ],
    "audioUrl": "/data/data/Tr_Eng_YDS_kelimeleri/audio_yds/compulsory.mp3"
  },
  {
    "id": 44,
    "word": "concede",
    "translation": "(istemeyerek de olsa) yenilgiyi/gerçeği kabul etmek",
    "pos": "verb",
    "tags": [
      "YDS"
    ],
    "audioUrl": "/data/data/Tr_Eng_YDS_kelimeleri/audio_yds/concede.mp3"
  },
  {
    "id": 45,
    "word": "concise",
    "translation": "kısa ve öz, veciz",
    "pos": "adjective",
    "tags": [
      "YDS"
    ],
    "audioUrl": "/data/data/Tr_Eng_YDS_kelimeleri/audio_yds/concise.mp3"
  },
  {
    "id": 46,
    "word": "condemn",
    "translation": "kınamak, mahkum etmek, cezalandırmak",
    "pos": "verb",
    "tags": [
      "YDS"
    ],
    "audioUrl": "/data/data/Tr_Eng_YDS_kelimeleri/audio_yds/condemn.mp3"
  },
  {
    "id": 47,
    "word": "condone",
    "translation": "göz yummak, affetmek, cezasız bırakmak",
    "pos": "verb",
    "tags": [
      "YDS"
    ],
    "audioUrl": "/data/data/Tr_Eng_YDS_kelimeleri/audio_yds/condone.mp3"
  },
  {
    "id": 48,
    "word": "conducive",
    "translation": "olasılık sağlayan, -e zemin hazırlayan, faydalı (-to ile)",
    "pos": "adjective",
    "tags": [
      "YDS"
    ],
    "audioUrl": "/data/data/Tr_Eng_YDS_kelimeleri/audio_yds/conducive.mp3"
  },
  {
    "id": 49,
    "word": "confide",
    "translation": "sırrını açmak, güvenip anlatmak (-in ile kullanılır)",
    "pos": "verb",
    "tags": [
      "YDS"
    ],
    "audioUrl": "/data/data/Tr_Eng_YDS_kelimeleri/audio_yds/confide.mp3"
  },
  {
    "id": 50,
    "word": "confinement",
    "translation": "hapis, sınırlandırma, lohusalık dönemi",
    "pos": "noun",
    "tags": [
      "YDS"
    ],
    "audioUrl": "/data/data/Tr_Eng_YDS_kelimeleri/audio_yds/confinement.mp3"
  },
  {
    "id": 51,
    "word": "confiscate",
    "translation": "el koymak, müsadere etmek, kamulaştırmak",
    "pos": "verb",
    "tags": [
      "YDS"
    ],
    "audioUrl": "/data/data/Tr_Eng_YDS_kelimeleri/audio_yds/confiscate.mp3"
  },
  {
    "id": 52,
    "word": "conscientious",
    "translation": "vicdanlı, dürüst, işini titizlikle yapan",
    "pos": "adjective",
    "tags": [
      "YDS"
    ],
    "audioUrl": "/data/data/Tr_Eng_YDS_kelimeleri/audio_yds/conscientious.mp3"
  },
  {
    "id": 53,
    "word": "consecutive",
    "translation": "ardışık, birbirini izleyen, aralıksız",
    "pos": "adjective",
    "tags": [
      "YDS"
    ],
    "audioUrl": "/data/data/Tr_Eng_YDS_kelimeleri/audio_yds/consecutive.mp3"
  },
  {
    "id": 54,
    "word": "consensus",
    "translation": "fikir birliği, mutabakat, genel uzlaşı",
    "pos": "noun",
    "tags": [
      "YDS"
    ],
    "audioUrl": "/data/data/Tr_Eng_YDS_kelimeleri/audio_yds/consensus.mp3"
  },
  {
    "id": 55,
    "word": "consent",
    "translation": "rıza, onay, izin / razı olmak",
    "pos": "noun/verb",
    "tags": [
      "YDS"
    ],
    "audioUrl": "/data/data/Tr_Eng_YDS_kelimeleri/audio_yds/consent.mp3"
  },
  {
    "id": 56,
    "word": "consequence",
    "translation": "sonuç, netice, ehemmiyet/önem",
    "pos": "noun",
    "tags": [
      "YDS"
    ],
    "audioUrl": "/data/data/Tr_Eng_YDS_kelimeleri/audio_yds/consequence.mp3"
  },
  {
    "id": 57,
    "word": "considerable",
    "translation": "önemli ölçüde, azımsanmayacak kadar çok",
    "pos": "adjective",
    "tags": [
      "YDS"
    ],
    "audioUrl": "/data/data/Tr_Eng_YDS_kelimeleri/audio_yds/considerable.mp3"
  },
  {
    "id": 58,
    "word": "conspicuous",
    "translation": "göze çarpan, belirgin, gizlenemez",
    "pos": "adjective",
    "tags": [
      "YDS"
    ],
    "audioUrl": "/data/data/Tr_Eng_YDS_kelimeleri/audio_yds/conspicuous.mp3"
  },
  {
    "id": 59,
    "word": "constitute",
    "translation": "oluşturmak, teşkil etmek, yasal olarak kurmak",
    "pos": "verb",
    "tags": [
      "YDS"
    ],
    "audioUrl": "/data/data/Tr_Eng_YDS_kelimeleri/audio_yds/constitute.mp3"
  },
  {
    "id": 60,
    "word": "constrain",
    "translation": "kısıtlamak, sınırlamak, baskı altına almak",
    "pos": "verb",
    "tags": [
      "YDS"
    ],
    "audioUrl": "/data/data/Tr_Eng_YDS_kelimeleri/audio_yds/constrain.mp3"
  },
  {
    "id": 61,
    "word": "contagious",
    "translation": "bulaşıcı (doğrudan temasla geçen)",
    "pos": "adjective",
    "tags": [
      "YDS"
    ],
    "audioUrl": "/data/data/Tr_Eng_YDS_kelimeleri/audio_yds/contagious.mp3"
  },
  {
    "id": 62,
    "word": "contaminate",
    "translation": "kirletmek, radyasyon/virüs bulaştırmak",
    "pos": "verb",
    "tags": [
      "YDS"
    ],
    "audioUrl": "/data/data/Tr_Eng_YDS_kelimeleri/audio_yds/contaminate.mp3"
  },
  {
    "id": 63,
    "word": "contemplate",
    "translation": "derin derin düşünmek, tasarlamak, kafa yormak",
    "pos": "verb",
    "tags": [
      "YDS"
    ],
    "audioUrl": "/data/data/Tr_Eng_YDS_kelimeleri/audio_yds/contemplate.mp3"
  },
  {
    "id": 64,
    "word": "contempt",
    "translation": "aşağılama, hor görme, küçümseme",
    "pos": "noun",
    "tags": [
      "YDS"
    ],
    "audioUrl": "/data/data/Tr_Eng_YDS_kelimeleri/audio_yds/contempt.mp3"
  },
  {
    "id": 65,
    "word": "contradict",
    "translation": "çelişmek, aksini iddia etmek, yalanlamak",
    "pos": "verb",
    "tags": [
      "YDS"
    ],
    "audioUrl": "/data/data/Tr_Eng_YDS_kelimeleri/audio_yds/contradict.mp3"
  },
  {
    "id": 66,
    "word": "controversial",
    "translation": "tartışmalı, kutuplaşmaya yol açan",
    "pos": "adjective",
    "tags": [
      "YDS"
    ],
    "audioUrl": "/data/data/Tr_Eng_YDS_kelimeleri/audio_yds/controversial.mp3"
  },
  {
    "id": 67,
    "word": "convene",
    "translation": "(meclis, kurul vb.) toplanmak, resmiyete çağırmak",
    "pos": "verb",
    "tags": [
      "YDS"
    ],
    "audioUrl": "/data/data/Tr_Eng_YDS_kelimeleri/audio_yds/convene.mp3"
  },
  {
    "id": 68,
    "word": "conventional",
    "translation": "geleneksel, alışılagelmiş, klasik (silah vb.)",
    "pos": "adjective",
    "tags": [
      "YDS"
    ],
    "audioUrl": "/data/data/Tr_Eng_YDS_kelimeleri/audio_yds/conventional.mp3"
  },
  {
    "id": 69,
    "word": "convey",
    "translation": "fikir/duygu aktarmak, nakletmek, taşımak",
    "pos": "verb",
    "tags": [
      "YDS"
    ],
    "audioUrl": "/data/data/Tr_Eng_YDS_kelimeleri/audio_yds/convey.mp3"
  },
  {
    "id": 70,
    "word": "cope",
    "translation": "(zorlukla) başa çıkmak, göğüs germek (-with ile)",
    "pos": "verb",
    "tags": [
      "YDS"
    ],
    "audioUrl": "/data/data/Tr_Eng_YKS_Kelimeleri/audio_yks/cope.mp3"
  },
  {
    "id": 71,
    "word": "cordial",
    "translation": "samimi, içten, dostane",
    "pos": "adjective",
    "tags": [
      "YDS"
    ],
    "audioUrl": "/data/data/Tr_Eng_YDS_kelimeleri/audio_yds/cordial.mp3"
  },
  {
    "id": 72,
    "word": "corroborate",
    "translation": "(delillerle) doğrulamak, desteklemek, teyit etmek",
    "pos": "verb",
    "tags": [
      "YDS"
    ],
    "audioUrl": "/data/data/Tr_Eng_YDS_kelimeleri/audio_yds/corroborate.mp3"
  },
  {
    "id": 73,
    "word": "counterfeit",
    "translation": "sahte / sahte şey (para vb.) / sahtesini yapmak",
    "pos": "adjective/noun/verb",
    "tags": [
      "YDS"
    ],
    "audioUrl": "/data/data/Tr_Eng_YDS_kelimeleri/audio_yds/counterfeit.mp3"
  },
  {
    "id": 74,
    "word": "counterpart",
    "translation": "karşıt makam, muadil, dengi, emsali",
    "pos": "noun",
    "tags": [
      "YDS"
    ],
    "audioUrl": "/data/data/Tr_Eng_YDS_kelimeleri/audio_yds/counterpart.mp3"
  },
  {
    "id": 75,
    "word": "craving",
    "translation": "aşırı istek, can atma, şiddetli arzu",
    "pos": "noun",
    "tags": [
      "YDS"
    ],
    "audioUrl": "/data/data/Tr_Eng_YDS_kelimeleri/audio_yds/craving.mp3"
  },
  {
    "id": 76,
    "word": "credible",
    "translation": "güvenilir, inanılır, akla yatkın",
    "pos": "adjective",
    "tags": [
      "YDS"
    ],
    "audioUrl": "/data/data/Tr_Eng_YDS_kelimeleri/audio_yds/credible.mp3"
  },
  {
    "id": 77,
    "word": "culpable",
    "translation": "suçlu, kusurlu, kabahatli",
    "pos": "adjective",
    "tags": [
      "YDS"
    ],
    "audioUrl": "/data/data/Tr_Eng_YDS_kelimeleri/audio_yds/culpable.mp3"
  },
  {
    "id": 48,
    "word": "curtail",
    "translation": "kısıtlamak, kesinti yapmak, vadesini azaltmak",
    "pos": "verb",
    "tags": [
      "YDS"
    ],
    "audioUrl": "/data/data/Tr_Eng_YDS_kelimeleri/audio_yds/curtail.mp3"
  },
  {
    "id": 79,
    "word": "cynical",
    "translation": "alaycı, insan iyiliğine inanmayan, sinik",
    "pos": "adjective",
    "tags": [
      "YDS"
    ],
    "audioUrl": "/data/data/Tr_Eng_YDS_kelimeleri/audio_yds/cynical.mp3"
  },
  {
    "id": 80,
    "word": "dawn",
    "translation": "şafak vakti, (tarihte) başlangıç / netleşmek/idrak etmek",
    "pos": "noun/verb",
    "tags": [
      "YDS"
    ],
    "audioUrl": "/data/data/Tr_Eng_YDS_kelimeleri/audio_yds/dawn.mp3"
  },
  {
    "id": 81,
    "word": "dearth",
    "translation": "kıtlık, yokluk, eksiklik",
    "pos": "noun",
    "tags": [
      "YDS"
    ],
    "audioUrl": "/data/data/Tr_Eng_YDS_kelimeleri/audio_yds/dearth.mp3"
  },
  {
    "id": 82,
    "word": "debilitate",
    "translation": "güçsüzleştirmek, zayıflatmak (hastalık/ekonomi vb.)",
    "pos": "verb",
    "tags": [
      "YDS"
    ],
    "audioUrl": "/data/data/Tr_Eng_YDS_kelimeleri/audio_yds/debilitate.mp3"
  },
  {
    "id": 83,
    "word": "decay",
    "translation": "çürümek, radyoaktif çözülmek / çürüme, bozulma",
    "pos": "verb/noun",
    "tags": [
      "YDS"
    ],
    "audioUrl": "/data/data/Tr_Eng_YDS_kelimeleri/audio_yds/decay.mp3"
  },
  {
    "id": 84,
    "word": "deceive",
    "translation": "aldatmak, kandırmak, hile yapmak",
    "pos": "verb",
    "tags": [
      "YDS"
    ],
    "audioUrl": "/data/data/Tr_Eng_YDS_kelimeleri/audio_yds/deceive.mp3"
  },
  {
    "id": 85,
    "word": "deceptive",
    "translation": "aldatıcı, yanıltıcı",
    "pos": "adjective",
    "tags": [
      "YDS"
    ],
    "audioUrl": "/data/data/Tr_Eng_YDS_kelimeleri/audio_yds/deceptive.mp3"
  },
  {
    "id": 86,
    "word": "decipher",
    "translation": "şifre çözmek, (kargacık yazıyı) okumak/anlamlandırmak",
    "pos": "verb",
    "tags": [
      "YDS"
    ],
    "audioUrl": "/data/data/Tr_Eng_YDS_kelimeleri/audio_yds/decipher.mp3"
  },
  {
    "id": 87,
    "word": "decline",
    "translation": "azalmak/çökmek, kibarca reddetmek / düşüş, azalma",
    "pos": "verb/noun",
    "tags": [
      "YDS"
    ],
    "audioUrl": "/data/data/Tr_Eng_YDS_kelimeleri/audio_yds/decline.mp3"
  },
  {
    "id": 88,
    "word": "decrepit",
    "translation": "eskimiş, çökmüş, yıpranmış, kocamış",
    "pos": "adjective",
    "tags": [
      "YDS"
    ],
    "audioUrl": "/data/data/Tr_Eng_YDS_kelimeleri/audio_yds/decrepit.mp3"
  },
  {
    "id": 89,
    "word": "dedicate",
    "translation": "kendini adamak, ithaf etmek (-to ile kullanılır)",
    "pos": "verb",
    "tags": [
      "YDS"
    ],
    "audioUrl": "/data/data/Tr_Eng_YDS_kelimeleri/audio_yds/dedicate.mp3"
  },
  {
    "id": 90,
    "word": "deduce",
    "translation": "tümdengelim yapmak, sonuç çıkarmak (-from ile)",
    "pos": "verb",
    "tags": [
      "YDS"
    ],
    "audioUrl": "/data/data/Tr_Eng_YDS_kelimeleri/audio_yds/deduce.mp3"
  },
  {
    "id": 91,
    "word": "defame",
    "translation": "iftira atmak, adını lekelemek, yermek",
    "pos": "verb",
    "tags": [
      "YDS"
    ],
    "audioUrl": "/data/data/Tr_Eng_YDS_kelimeleri/audio_yds/defame.mp3"
  },
  {
    "id": 92,
    "word": "defect",
    "translation": "kusur, defo / saf değiştirmek, ülkeden kaçmak (-from)",
    "pos": "noun/verb",
    "tags": [
      "YDS"
    ],
    "audioUrl": "/data/data/Tr_Eng_YDS_kelimeleri/audio_yds/defect.mp3"
  },
  {
    "id": 93,
    "word": "deference",
    "translation": "saygı, hürmet, baş eğme",
    "pos": "noun",
    "tags": [
      "YDS"
    ],
    "audioUrl": "/data/data/Tr_Eng_YDS_kelimeleri/audio_yds/deference.mp3"
  },
  {
    "id": 94,
    "word": "deficiency",
    "translation": "yetersizlik, (vitamin vb.) eksikliği",
    "pos": "noun",
    "tags": [
      "YDS"
    ],
    "audioUrl": "/data/data/Tr_Eng_YDS_kelimeleri/audio_yds/deficiency.mp3"
  },
  {
    "id": 95,
    "word": "deficit",
    "translation": "(bütçe, dış ticaret vb.) açığı, fire",
    "pos": "noun",
    "tags": [
      "YDS"
    ],
    "audioUrl": "/data/data/Tr_Eng_YDS_kelimeleri/audio_yds/deficit.mp3"
  },
  {
    "id": 96,
    "word": "defy",
    "translation": "karşı gelmek, meydan okumak, kanuna uymamak",
    "pos": "verb",
    "tags": [
      "YDS"
    ],
    "audioUrl": "/data/data/Tr_Eng_YDS_kelimeleri/audio_yds/defy.mp3"
  },
  {
    "id": 97,
    "word": "degenerate",
    "translation": "yozlaşmak, dejenere olmak / yozlaşmış",
    "pos": "verb/adjective",
    "tags": [
      "YDS"
    ],
    "audioUrl": "/data/data/Tr_Eng_YDS_kelimeleri/audio_yds/degenerate.mp3"
  },
  {
    "id": 98,
    "word": "degrade",
    "translation": "itibarını zedelemek, aşağılamak, kalitesini düşürmek",
    "pos": "verb",
    "tags": [
      "YDS"
    ],
    "audioUrl": "/data/data/Tr_Eng_YDS_kelimeleri/audio_yds/degrade.mp3"
  },
  {
    "id": 99,
    "word": "deliberate",
    "translation": "kasti, bilerek yapılan / üzerinde uzunca tartışmak",
    "pos": "adjective/verb",
    "tags": [
      "YDS"
    ],
    "audioUrl": "/data/data/Tr_Eng_YDS_kelimeleri/audio_yds/deliberate.mp3"
  },
  {
    "id": 100,
    "word": "delicate",
    "translation": "hassas, narin, ince işçilik isteyen",
    "pos": "adjective",
    "tags": [
      "YDS"
    ],
    "audioUrl": "/data/data/Tr_Eng_YDS_kelimeleri/audio_yds/delicate.mp3"
  }
]